Workbook

Sheet Dashboard
A1: NIFTY 50 Valuation & Forward-Return Tracker
A2: Methodology-adjusted valuation signal. BUY / HOLD / SELL is a long-horizon allocation signal, not a short-term trading call or a recommendation to short the index.
A4: LIVE SIGNAL
A5: As of | B5: 46283 | D5: =B20
A6: NIFTY 50 Close | B6: 23346.4
A7: Current P/E | B7: 19.74
A8: Earnings Yield | B8: =IFERROR(1/B7,"")
A9: Post-2021 P/E Percentile | B9: =IFERROR((COUNTIF(PE_History_Post2021!$B$5:$B$2000,"<"&B7)+0.5*COUNTIF(PE_History_Post2021!$B$5:$B$2000,B7))/COUNT(PE_History_Post2021!$B$5:$B$2000),"")
A10: Era Median P/E | B10: =IFERROR(MEDIAN(PE_History_Post2021!$B$5:$B$2000),"") | D10: =IF(B20="BUY","Valuation is unusually low versus the consolidated-earnings era; gradual allocation is historically favoured.",IF(B20="HOLD","Valuation/growth mix is neutral; maintain strategic allocation.","Valuation/growth mix is unfavourable; consider reducing fresh allocation rather than shorting."))
A11: Current Implied EPS | B11: =IFERROR(B6/B7,"")
A12: Prior-year comparison month | B12: 45930
A13: Prior-year NIFTY close | B13: 24691.95
A14: Prior-year P/E | B14: 21.8
A15: Prior-year Implied EPS | B15: =IFERROR(B13/B14,"")
A16: Approx. YoY Implied EPS Growth | B16: =IFERROR(B11/B15-1,"")
A17: Valuation Score | B17: =IF(B9="","",100*(1-B9))
A18: Growth Score | B18: =IF(B16="","",IF(B16<=0,20,IF(B16<5%,20+400*B16,IF(B16<10%,40+400*(B16-5%),IF(B16<15%,60+400*(B16-10%),IF(B16<25%,80+200*(B16-15%),100))))))
A19: Composite Score | B19: =IF(OR(B17="",B18=""),"",70%*B17+30%*B18)
A20: Signal | B20: =IF(B19="","",IF(B19>=70,"BUY",IF(B19>=40,"HOLD","SELL")))
A23: SIGNAL RULE
A24: Component | B24: Weight | C24: Definition
A25: Valuation percentile | B25: 70% | C25: Lower regime-relative P/E = higher score
A26: YoY implied EPS growth | B26: 30% | C26: Higher index EPS growth = higher score
A27: BUY | B27: Score ≥ 70 | C27: Long-horizon valuation signal
A28: HOLD | B28: 40 ≤ Score < 70 | C28: Neutral / maintain strategic allocation
A29: SELL | B29: Score < 40 | C29: Reduce/avoid fresh allocation; not a short call
A31: REGIME-NORMALISED BACKTEST — MEDIAN FORWARD PRICE RETURNS
A32: Valuation Quintile | B32: 1Y | C32: 3Y CAGR | D32: 5Y CAGR | E32: 10Y CAGR
A33: Q1 Cheapest | B33: =Backtest!D6 | C33: =Backtest!D15 | D33: =Backtest!D24 | E33: =Backtest!D33
A34: Q2 | B34: =Backtest!D7 | C34: =Backtest!D16 | D34: =Backtest!D25 | E34: =Backtest!D34
A35: Q3 | B35: =Backtest!D8 | C35: =Backtest!D17 | D35: =Backtest!D26 | E35: =Backtest!D35
A36: Q4 | B36: =Backtest!D9 | C36: =Backtest!D18 | D36: =Backtest!D27 | E36: =Backtest!D36
A37: Q5 Most Expensive | B37: =Backtest!D10 | C37: =Backtest!D19 | D37: =Backtest!D28 | E37: =Backtest!D37

Sheet Backtest
A1: Regime-Normalised P/E vs Forward NIFTY 50 Returns
A2: Each P/E observation is ranked only against its own methodology regime. Quarter-end sampling is used to reduce overlap. Returns are price returns, not TRI.
A4: 1-YEAR FORWARD RETURN
A5: Valuation Quintile | B5: N | C5: Average | D5: Median | E5: Positive % | F5: Loss % | G5: Worst | H5: Best
A6: Q1 Cheapest | B6: =COUNTIFS(Quarterly_Data!$H$5:$H$114,A6,Quarterly_Data!$I$5:$I$114,"<>") | C6: =IFERROR(AVERAGEIFS(Quarterly_Data!$I$5:$I$114,Quarterly_Data!$H$5:$H$114,A6),"") | D6: =IFERROR(AGGREGATE(12,6,Quarterly_Data!$I$5:$I$114/(Quarterly_Data!$H$5:$H$114=A6)),"") | E6: =IFERROR(COUNTIFS(Quarterly_Data!$H$5:$H$114,A6,Quarterly_Data!$I$5:$I$114,">0")/B6,"") | F6: =IFERROR(COUNTIFS(Quarterly_Data!$H$5:$H$114,A6,Quarterly_Data!$I$5:$I$114,"<0")/B6,"") | G6: =IFERROR(MINIFS(Quarterly_Data!$I$5:$I$114,Quarterly_Data!$H$5:$H$114,A6),"") | H6: =IFERROR(MAXIFS(Quarterly_Data!$I$5:$I$114,Quarterly_Data!$H$5:$H$114,A6),"")
A7: Q2 | B7: =COUNTIFS(Quarterly_Data!$H$5:$H$114,A7,Quarterly_Data!$I$5:$I$114,"<>") | C7: =IFERROR(AVERAGEIFS(Quarterly_Data!$I$5:$I$114,Quarterly_Data!$H$5:$H$114,A7),"") | D7: =IFERROR(AGGREGATE(12,6,Quarterly_Data!$I$5:$I$114/(Quarterly_Data!$H$5:$H$114=A7)),"") | E7: =IFERROR(COUNTIFS(Quarterly_Data!$H$5:$H$114,A7,Quarterly_Data!$I$5:$I$114,">0")/B7,"") | F7: =IFERROR(COUNTIFS(Quarterly_Data!$H$5:$H$114,A7,Quarterly_Data!$I$5:$I$114,"<0")/B7,"") | G7: =IFERROR(MINIFS(Quarterly_Data!$I$5:$I$114,Quarterly_Data!$H$5:$H$114,A7),"") | H7: =IFERROR(MAXIFS(Quarterly_Data!$I$5:$I$114,Quarterly_Data!$H$5:$H$114,A7),"")
A8: Q3 | B8: =COUNTIFS(Quarterly_Data!$H$5:$H$114,A8,Quarterly_Data!$I$5:$I$114,"<>") | C8: =IFERROR(AVERAGEIFS(Quarterly_Data!$I$5:$I$114,Quarterly_Data!$H$5:$H$114,A8),"") | D8: =IFERROR(AGGREGATE(12,6,Quarterly_Data!$I$5:$I$114/(Quarterly_Data!$H$5:$H$114=A8)),"") | E8: =IFERROR(COUNTIFS(Quarterly_Data!$H$5:$H$114,A8,Quarterly_Data!$I$5:$I$114,">0")/B8,"") | F8: =IFERROR(COUNTIFS(Quarterly_Data!$H$5:$H$114,A8,Quarterly_Data!$I$5:$I$114,"<0")/B8,"") | G8: =IFERROR(MINIFS(Quarterly_Data!$I$5:$I$114,Quarterly_Data!$H$5:$H$114,A8),"") | H8: =IFERROR(MAXIFS(Quarterly_Data!$I$5:$I$114,Quarterly_Data!$H$5:$H$114,A8),"")
A9: Q4 | B9: =COUNTIFS(Quarterly_Data!$H$5:$H$114,A9,Quarterly_Data!$I$5:$I$114,"<>") | C9: =IFERROR(AVERAGEIFS(Quarterly_Data!$I$5:$I$114,Quarterly_Data!$H$5:$H$114,A9),"") | D9: =IFERROR(AGGREGATE(12,6,Quarterly_Data!$I$5:$I$114/(Quarterly_Data!$H$5:$H$114=A9)),"") | E9: =IFERROR(COUNTIFS(Quarterly_Data!$H$5:$H$114,A9,Quarterly_Data!$I$5:$I$114,">0")/B9,"") | F9: =IFERROR(COUNTIFS(Quarterly_Data!$H$5:$H$114,A9,Quarterly_Data!$I$5:$I$114,"<0")/B9,"") | G9: =IFERROR(MINIFS(Quarterly_Data!$I$5:$I$114,Quarterly_Data!$H$5:$H$114,A9),"") | H9: =IFERROR(MAXIFS(Quarterly_Data!$I$5:$I$114,Quarterly_Data!$H$5:$H$114,A9),"")
A10: Q5 Most Expensive | B10: =COUNTIFS(Quarterly_Data!$H$5:$H$114,A10,Quarterly_Data!$I$5:$I$114,"<>") | C10: =IFERROR(AVERAGEIFS(Quarterly_Data!$I$5:$I$114,Quarterly_Data!$H$5:$H$114,A10),"") | D10: =IFERROR(AGGREGATE(12,6,Quarterly_Data!$I$5:$I$114/(Quarterly_Data!$H$5:$H$114=A10)),"") | E10: =IFERROR(COUNTIFS(Quarterly_Data!$H$5:$H$114,A10,Quarterly_Data!$I$5:$I$114,">0")/B10,"") | F10: =IFERROR(COUNTIFS(Quarterly_Data!$H$5:$H$114,A10,Quarterly_Data!$I$5:$I$114,"<0")/B10,"") | G10: =IFERROR(MINIFS(Quarterly_Data!$I$5:$I$114,Quarterly_Data!$H$5:$H$114,A10),"") | H10: =IFERROR(MAXIFS(Quarterly_Data!$I$5:$I$114,Quarterly_Data!$H$5:$H$114,A10),"")
A13: 3-YEAR FORWARD CAGR
A14: Valuation Quintile | B14: N | C14: Average | D14: Median | E14: Positive % | F14: Loss % | G14: Worst | H14: Best
A15: Q1 Cheapest | B15: =COUNTIFS(Quarterly_Data!$H$5:$H$114,A15,Quarterly_Data!$J$5:$J$114,"<>") | C15: =IFERROR(AVERAGEIFS(Quarterly_Data!$J$5:$J$114,Quarterly_Data!$H$5:$H$114,A15),"") | D15: =IFERROR(AGGREGATE(12,6,Quarterly_Data!$J$5:$J$114/(Quarterly_Data!$H$5:$H$114=A15)),"") | E15: =IFERROR(COUNTIFS(Quarterly_Data!$H$5:$H$114,A15,Quarterly_Data!$J$5:$J$114,">0")/B15,"") | F15: =IFERROR(COUNTIFS(Quarterly_Data!$H$5:$H$114,A15,Quarterly_Data!$J$5:$J$114,"<0")/B15,"") | G15: =IFERROR(MINIFS(Quarterly_Data!$J$5:$J$114,Quarterly_Data!$H$5:$H$114,A15),"") | H15: =IFERROR(MAXIFS(Quarterly_Data!$J$5:$J$114,Quarterly_Data!$H$5:$H$114,A15),"")
A16: Q2 | B16: =COUNTIFS(Quarterly_Data!$H$5:$H$114,A16,Quarterly_Data!$J$5:$J$114,"<>") | C16: =IFERROR(AVERAGEIFS(Quarterly_Data!$J$5:$J$114,Quarterly_Data!$H$5:$H$114,A16),"") | D16: =IFERROR(AGGREGATE(12,6,Quarterly_Data!$J$5:$J$114/(Quarterly_Data!$H$5:$H$114=A16)),"") | E16: =IFERROR(COUNTIFS(Quarterly_Data!$H$5:$H$114,A16,Quarterly_Data!$J$5:$J$114,">0")/B16,"") | F16: =IFERROR(COUNTIFS(Quarterly_Data!$H$5:$H$114,A16,Quarterly_Data!$J$5:$J$114,"<0")/B16,"") | G16: =IFERROR(MINIFS(Quarterly_Data!$J$5:$J$114,Quarterly_Data!$H$5:$H$114,A16),"") | H16: =IFERROR(MAXIFS(Quarterly_Data!$J$5:$J$114,Quarterly_Data!$H$5:$H$114,A16),"")
A17: Q3 | B17: =COUNTIFS(Quarterly_Data!$H$5:$H$114,A17,Quarterly_Data!$J$5:$J$114,"<>") | C17: =IFERROR(AVERAGEIFS(Quarterly_Data!$J$5:$J$114,Quarterly_Data!$H$5:$H$114,A17),"") | D17: =IFERROR(AGGREGATE(12,6,Quarterly_Data!$J$5:$J$114/(Quarterly_Data!$H$5:$H$114=A17)),"") | E17: =IFERROR(COUNTIFS(Quarterly_Data!$H$5:$H$114,A17,Quarterly_Data!$J$5:$J$114,">0")/B17,"") | F17: =IFERROR(COUNTIFS(Quarterly_Data!$H$5:$H$114,A17,Quarterly_Data!$J$5:$J$114,"<0")/B17,"") | G17: =IFERROR(MINIFS(Quarterly_Data!$J$5:$J$114,Quarterly_Data!$H$5:$H$114,A17),"") | H17: =IFERROR(MAXIFS(Quarterly_Data!$J$5:$J$114,Quarterly_Data!$H$5:$H$114,A17),"")
A18: Q4 | B18: =COUNTIFS(Quarterly_Data!$H$5:$H$114,A18,Quarterly_Data!$J$5:$J$114,"<>") | C18: =IFERROR(AVERAGEIFS(Quarterly_Data!$J$5:$J$114,Quarterly_Data!$H$5:$H$114,A18),"") | D18: =IFERROR(AGGREGATE(12,6,Quarterly_Data!$J$5:$J$114/(Quarterly_Data!$H$5:$H$114=A18)),"") | E18: =IFERROR(COUNTIFS(Quarterly_Data!$H$5:$H$114,A18,Quarterly_Data!$J$5:$J$114,">0")/B18,"") | F18: =IFERROR(COUNTIFS(Quarterly_Data!$H$5:$H$114,A18,Quarterly_Data!$J$5:$J$114,"<0")/B18,"") | G18: =IFERROR(MINIFS(Quarterly_Data!$J$5:$J$114,Quarterly_Data!$H$5:$H$114,A18),"") | H18: =IFERROR(MAXIFS(Quarterly_Data!$J$5:$J$114,Quarterly_Data!$H$5:$H$114,A18),"")
A19: Q5 Most Expensive | B19: =COUNTIFS(Quarterly_Data!$H$5:$H$114,A19,Quarterly_Data!$J$5:$J$114,"<>") | C19: =IFERROR(AVERAGEIFS(Quarterly_Data!$J$5:$J$114,Quarterly_Data!$H$5:$H$114,A19),"") | D19: =IFERROR(AGGREGATE(12,6,Quarterly_Data!$J$5:$J$114/(Quarterly_Data!$H$5:$H$114=A19)),"") | E19: =IFERROR(COUNTIFS(Quarterly_Data!$H$5:$H$114,A19,Quarterly_Data!$J$5:$J$114,">0")/B19,"") | F19: =IFERROR(COUNTIFS(Quarterly_Data!$H$5:$H$114,A19,Quarterly_Data!$J$5:$J$114,"<0")/B19,"") | G19: =IFERROR(MINIFS(Quarterly_Data!$J$5:$J$114,Quarterly_Data!$H$5:$H$114,A19),"") | H19: =IFERROR(MAXIFS(Quarterly_Data!$J$5:$J$114,Quarterly_Data!$H$5:$H$114,A19),"")
A22: 5-YEAR FORWARD CAGR
A23: Valuation Quintile | B23: N | C23: Average | D23: Median | E23: Positive % | F23: Loss % | G23: Worst | H23: Best
A24: Q1 Cheapest | B24: =COUNTIFS(Quarterly_Data!$H$5:$H$114,A24,Quarterly_Data!$K$5:$K$114,"<>") | C24: =IFERROR(AVERAGEIFS(Quarterly_Data!$K$5:$K$114,Quarterly_Data!$H$5:$H$114,A24),"") | D24: =IFERROR(AGGREGATE(12,6,Quarterly_Data!$K$5:$K$114/(Quarterly_Data!$H$5:$H$114=A24)),"") | E24: =IFERROR(COUNTIFS(Quarterly_Data!$H$5:$H$114,A24,Quarterly_Data!$K$5:$K$114,">0")/B24,"") | F24: =IFERROR(COUNTIFS(Quarterly_Data!$H$5:$H$114,A24,Quarterly_Data!$K$5:$K$114,"<0")/B24,"") | G24: =IFERROR(MINIFS(Quarterly_Data!$K$5:$K$114,Quarterly_Data!$H$5:$H$114,A24),"") | H24: =IFERROR(MAXIFS(Quarterly_Data!$K$5:$K$114,Quarterly_Data!$H$5:$H$114,A24),"")
A25: Q2 | B25: =COUNTIFS(Quarterly_Data!$H$5:$H$114,A25,Quarterly_Data!$K$5:$K$114,"<>") | C25: =IFERROR(AVERAGEIFS(Quarterly_Data!$K$5:$K$114,Quarterly_Data!$H$5:$H$114,A25),"") | D25: =IFERROR(AGGREGATE(12,6,Quarterly_Data!$K$5:$K$114/(Quarterly_Data!$H$5:$H$114=A25)),"") | E25: =IFERROR(COUNTIFS(Quarterly_Data!$H$5:$H$114,A25,Quarterly_Data!$K$5:$K$114,">0")/B25,"") | F25: =IFERROR(COUNTIFS(Quarterly_Data!$H$5:$H$114,A25,Quarterly_Data!$K$5:$K$114,"<0")/B25,"") | G25: =IFERROR(MINIFS(Quarterly_Data!$K$5:$K$114,Quarterly_Data!$H$5:$H$114,A25),"") | H25: =IFERROR(MAXIFS(Quarterly_Data!$K$5:$K$114,Quarterly_Data!$H$5:$H$114,A25),"")
A26: Q3 | B26: =COUNTIFS(Quarterly_Data!$H$5:$H$114,A26,Quarterly_Data!$K$5:$K$114,"<>") | C26: =IFERROR(AVERAGEIFS(Quarterly_Data!$K$5:$K$114,Quarterly_Data!$H$5:$H$114,A26),"") | D26: =IFERROR(AGGREGATE(12,6,Quarterly_Data!$K$5:$K$114/(Quarterly_Data!$H$5:$H$114=A26)),"") | E26: =IFERROR(COUNTIFS(Quarterly_Data!$H$5:$H$114,A26,Quarterly_Data!$K$5:$K$114,">0")/B26,"") | F26: =IFERROR(COUNTIFS(Quarterly_Data!$H$5:$H$114,A26,Quarterly_Data!$K$5:$K$114,"<0")/B26,"") | G26: =IFERROR(MINIFS(Quarterly_Data!$K$5:$K$114,Quarterly_Data!$H$5:$H$114,A26),"") | H26: =IFERROR(MAXIFS(Quarterly_Data!$K$5:$K$114,Quarterly_Data!$H$5:$H$114,A26),"")
A27: Q4 | B27: =COUNTIFS(Quarterly_Data!$H$5:$H$114,A27,Quarterly_Data!$K$5:$K$114,"<>") | C27: =IFERROR(AVERAGEIFS(Quarterly_Data!$K$5:$K$114,Quarterly_Data!$H$5:$H$114,A27),"") | D27: =IFERROR(AGGREGATE(12,6,Quarterly_Data!$K$5:$K$114/(Quarterly_Data!$H$5:$H$114=A27)),"") | E27: =IFERROR(COUNTIFS(Quarterly_Data!$H$5:$H$114,A27,Quarterly_Data!$K$5:$K$114,">0")/B27,"") | F27: =IFERROR(COUNTIFS(Quarterly_Data!$H$5:$H$114,A27,Quarterly_Data!$K$5:$K$114,"<0")/B27,"") | G27: =IFERROR(MINIFS(Quarterly_Data!$K$5:$K$114,Quarterly_Data!$H$5:$H$114,A27),"") | H27: =IFERROR(MAXIFS(Quarterly_Data!$K$5:$K$114,Quarterly_Data!$H$5:$H$114,A27),"")
A28: Q5 Most Expensive | B28: =COUNTIFS(Quarterly_Data!$H$5:$H$114,A28,Quarterly_Data!$K$5:$K$114,"<>") | C28: =IFERROR(AVERAGEIFS(Quarterly_Data!$K$5:$K$114,Quarterly_Data!$H$5:$H$114,A28),"") | D28: =IFERROR(AGGREGATE(12,6,Quarterly_Data!$K$5:$K$114/(Quarterly_Data!$H$5:$H$114=A28)),"") | E28: =IFERROR(COUNTIFS(Quarterly_Data!$H$5:$H$114,A28,Quarterly_Data!$K$5:$K$114,">0")/B28,"") | F28: =IFERROR(COUNTIFS(Quarterly_Data!$H$5:$H$114,A28,Quarterly_Data!$K$5:$K$114,"<0")/B28,"") | G28: =IFERROR(MINIFS(Quarterly_Data!$K$5:$K$114,Quarterly_Data!$H$5:$H$114,A28),"") | H28: =IFERROR(MAXIFS(Quarterly_Data!$K$5:$K$114,Quarterly_Data!$H$5:$H$114,A28),"")
A31: 10-YEAR FORWARD CAGR
A32: Valuation Quintile | B32: N | C32: Average | D32: Median | E32: Positive % | F32: Loss % | G32: Worst | H32: Best
A33: Q1 Cheapest | B33: =COUNTIFS(Quarterly_Data!$H$5:$H$114,A33,Quarterly_Data!$L$5:$L$114,"<>") | C33: =IFERROR(AVERAGEIFS(Quarterly_Data!$L$5:$L$114,Quarterly_Data!$H$5:$H$114,A33),"") | D33: =IFERROR(AGGREGATE(12,6,Quarterly_Data!$L$5:$L$114/(Quarterly_Data!$H$5:$H$114=A33)),"") | E33: =IFERROR(COUNTIFS(Quarterly_Data!$H$5:$H$114,A33,Quarterly_Data!$L$5:$L$114,">0")/B33,"") | F33: =IFERROR(COUNTIFS(Quarterly_Data!$H$5:$H$114,A33,Quarterly_Data!$L$5:$L$114,"<0")/B33,"") | G33: =IFERROR(MINIFS(Quarterly_Data!$L$5:$L$114,Quarterly_Data!$H$5:$H$114,A33),"") | H33: =IFERROR(MAXIFS(Quarterly_Data!$L$5:$L$114,Quarterly_Data!$H$5:$H$114,A33),"")
A34: Q2 | B34: =COUNTIFS(Quarterly_Data!$H$5:$H$114,A34,Quarterly_Data!$L$5:$L$114,"<>") | C34: =IFERROR(AVERAGEIFS(Quarterly_Data!$L$5:$L$114,Quarterly_Data!$H$5:$H$114,A34),"") | D34: =IFERROR(AGGREGATE(12,6,Quarterly_Data!$L$5:$L$114/(Quarterly_Data!$H$5:$H$114=A34)),"") | E34: =IFERROR(COUNTIFS(Quarterly_Data!$H$5:$H$114,A34,Quarterly_Data!$L$5:$L$114,">0")/B34,"") | F34: =IFERROR(COUNTIFS(Quarterly_Data!$H$5:$H$114,A34,Quarterly_Data!$L$5:$L$114,"<0")/B34,"") | G34: =IFERROR(MINIFS(Quarterly_Data!$L$5:$L$114,Quarterly_Data!$H$5:$H$114,A34),"") | H34: =IFERROR(MAXIFS(Quarterly_Data!$L$5:$L$114,Quarterly_Data!$H$5:$H$114,A34),"")
A35: Q3 | B35: =COUNTIFS(Quarterly_Data!$H$5:$H$114,A35,Quarterly_Data!$L$5:$L$114,"<>") | C35: =IFERROR(AVERAGEIFS(Quarterly_Data!$L$5:$L$114,Quarterly_Data!$H$5:$H$114,A35),"") | D35: =IFERROR(AGGREGATE(12,6,Quarterly_Data!$L$5:$L$114/(Quarterly_Data!$H$5:$H$114=A35)),"") | E35: =IFERROR(COUNTIFS(Quarterly_Data!$H$5:$H$114,A35,Quarterly_Data!$L$5:$L$114,">0")/B35,"") | F35: =IFERROR(COUNTIFS(Quarterly_Data!$H$5:$H$114,A35,Quarterly_Data!$L$5:$L$114,"<0")/B35,"") | G35: =IFERROR(MINIFS(Quarterly_Data!$L$5:$L$114,Quarterly_Data!$H$5:$H$114,A35),"") | H35: =IFERROR(MAXIFS(Quarterly_Data!$L$5:$L$114,Quarterly_Data!$H$5:$H$114,A35),"")
A36: Q4 | B36: =COUNTIFS(Quarterly_Data!$H$5:$H$114,A36,Quarterly_Data!$L$5:$L$114,"<>") | C36: =IFERROR(AVERAGEIFS(Quarterly_Data!$L$5:$L$114,Quarterly_Data!$H$5:$H$114,A36),"") | D36: =IFERROR(AGGREGATE(12,6,Quarterly_Data!$L$5:$L$114/(Quarterly_Data!$H$5:$H$114=A36)),"") | E36: =IFERROR(COUNTIFS(Quarterly_Data!$H$5:$H$114,A36,Quarterly_Data!$L$5:$L$114,">0")/B36,"") | F36: =IFERROR(COUNTIFS(Quarterly_Data!$H$5:$H$114,A36,Quarterly_Data!$L$5:$L$114,"<0")/B36,"") | G36: =IFERROR(MINIFS(Quarterly_Data!$L$5:$L$114,Quarterly_Data!$H$5:$H$114,A36),"") | H36: =IFERROR(MAXIFS(Quarterly_Data!$L$5:$L$114,Quarterly_Data!$H$5:$H$114,A36),"")
A37: Q5 Most Expensive | B37: =COUNTIFS(Quarterly_Data!$H$5:$H$114,A37,Quarterly_Data!$L$5:$L$114,"<>") | C37: =IFERROR(AVERAGEIFS(Quarterly_Data!$L$5:$L$114,Quarterly_Data!$H$5:$H$114,A37),"") | D37: =IFERROR(AGGREGATE(12,6,Quarterly_Data!$L$5:$L$114/(Quarterly_Data!$H$5:$H$114=A37)),"") | E37: =IFERROR(COUNTIFS(Quarterly_Data!$H$5:$H$114,A37,Quarterly_Data!$L$5:$L$114,">0")/B37,"") | F37: =IFERROR(COUNTIFS(Quarterly_Data!$H$5:$H$114,A37,Quarterly_Data!$L$5:$L$114,"<0")/B37,"") | G37: =IFERROR(MINIFS(Quarterly_Data!$L$5:$L$114,Quarterly_Data!$H$5:$H$114,A37),"") | H37: =IFERROR(MAXIFS(Quarterly_Data!$L$5:$L$114,Quarterly_Data!$H$5:$H$114,A37),"")
A40: Note: The Q5 bucket contains the 2020–21 earnings-collapse episode, which can make very high trailing P/E look better than a normal expensive market. Use the direction and distribution, not a single point estimate.

Sheet Growth_Matrix
A1: Valuation × Earnings Growth Matrix
A2: Average forward price CAGR by regime-normalised valuation quintile and YoY implied NIFTY EPS growth. Small cell counts are shown underneath and should be treated cautiously.
A4: 3-YEAR FORWARD CAGR — AVERAGE
A5: EPS Growth | B5: Q1 Cheapest | C5: Q2 | D5: Q3 | E5: Q4 | F5: Q5 Most Expensive
A6: <5% | B6: =IFERROR(AVERAGEIFS(Quarterly_Data!$J$5:$J$114,Quarterly_Data!$H$5:$H$114,B$5,Quarterly_Data!$M$5:$M$114,$A6),"") | C6: =IFERROR(AVERAGEIFS(Quarterly_Data!$J$5:$J$114,Quarterly_Data!$H$5:$H$114,C$5,Quarterly_Data!$M$5:$M$114,$A6),"") | D6: =IFERROR(AVERAGEIFS(Quarterly_Data!$J$5:$J$114,Quarterly_Data!$H$5:$H$114,D$5,Quarterly_Data!$M$5:$M$114,$A6),"") | E6: =IFERROR(AVERAGEIFS(Quarterly_Data!$J$5:$J$114,Quarterly_Data!$H$5:$H$114,E$5,Quarterly_Data!$M$5:$M$114,$A6),"") | F6: =IFERROR(AVERAGEIFS(Quarterly_Data!$J$5:$J$114,Quarterly_Data!$H$5:$H$114,F$5,Quarterly_Data!$M$5:$M$114,$A6),"")
A7: 5-15% | B7: =IFERROR(AVERAGEIFS(Quarterly_Data!$J$5:$J$114,Quarterly_Data!$H$5:$H$114,B$5,Quarterly_Data!$M$5:$M$114,$A7),"") | C7: =IFERROR(AVERAGEIFS(Quarterly_Data!$J$5:$J$114,Quarterly_Data!$H$5:$H$114,C$5,Quarterly_Data!$M$5:$M$114,$A7),"") | D7: =IFERROR(AVERAGEIFS(Quarterly_Data!$J$5:$J$114,Quarterly_Data!$H$5:$H$114,D$5,Quarterly_Data!$M$5:$M$114,$A7),"") | E7: =IFERROR(AVERAGEIFS(Quarterly_Data!$J$5:$J$114,Quarterly_Data!$H$5:$H$114,E$5,Quarterly_Data!$M$5:$M$114,$A7),"") | F7: =IFERROR(AVERAGEIFS(Quarterly_Data!$J$5:$J$114,Quarterly_Data!$H$5:$H$114,F$5,Quarterly_Data!$M$5:$M$114,$A7),"")
A8: >15% | B8: =IFERROR(AVERAGEIFS(Quarterly_Data!$J$5:$J$114,Quarterly_Data!$H$5:$H$114,B$5,Quarterly_Data!$M$5:$M$114,$A8),"") | C8: =IFERROR(AVERAGEIFS(Quarterly_Data!$J$5:$J$114,Quarterly_Data!$H$5:$H$114,C$5,Quarterly_Data!$M$5:$M$114,$A8),"") | D8: =IFERROR(AVERAGEIFS(Quarterly_Data!$J$5:$J$114,Quarterly_Data!$H$5:$H$114,D$5,Quarterly_Data!$M$5:$M$114,$A8),"") | E8: =IFERROR(AVERAGEIFS(Quarterly_Data!$J$5:$J$114,Quarterly_Data!$H$5:$H$114,E$5,Quarterly_Data!$M$5:$M$114,$A8),"") | F8: =IFERROR(AVERAGEIFS(Quarterly_Data!$J$5:$J$114,Quarterly_Data!$H$5:$H$114,F$5,Quarterly_Data!$M$5:$M$114,$A8),"")
A10: Observation count (N)
A11: <5% | B11: =COUNTIFS(Quarterly_Data!$H$5:$H$114,B$5,Quarterly_Data!$M$5:$M$114,$A11,Quarterly_Data!$J$5:$J$114,"<>") | C11: =COUNTIFS(Quarterly_Data!$H$5:$H$114,C$5,Quarterly_Data!$M$5:$M$114,$A11,Quarterly_Data!$J$5:$J$114,"<>") | D11: =COUNTIFS(Quarterly_Data!$H$5:$H$114,D$5,Quarterly_Data!$M$5:$M$114,$A11,Quarterly_Data!$J$5:$J$114,"<>") | E11: =COUNTIFS(Quarterly_Data!$H$5:$H$114,E$5,Quarterly_Data!$M$5:$M$114,$A11,Quarterly_Data!$J$5:$J$114,"<>") | F11: =COUNTIFS(Quarterly_Data!$H$5:$H$114,F$5,Quarterly_Data!$M$5:$M$114,$A11,Quarterly_Data!$J$5:$J$114,"<>")
A12: 5-15% | B12: =COUNTIFS(Quarterly_Data!$H$5:$H$114,B$5,Quarterly_Data!$M$5:$M$114,$A12,Quarterly_Data!$J$5:$J$114,"<>") | C12: =COUNTIFS(Quarterly_Data!$H$5:$H$114,C$5,Quarterly_Data!$M$5:$M$114,$A12,Quarterly_Data!$J$5:$J$114,"<>") | D12: =COUNTIFS(Quarterly_Data!$H$5:$H$114,D$5,Quarterly_Data!$M$5:$M$114,$A12,Quarterly_Data!$J$5:$J$114,"<>") | E12: =COUNTIFS(Quarterly_Data!$H$5:$H$114,E$5,Quarterly_Data!$M$5:$M$114,$A12,Quarterly_Data!$J$5:$J$114,"<>") | F12: =COUNTIFS(Quarterly_Data!$H$5:$H$114,F$5,Quarterly_Data!$M$5:$M$114,$A12,Quarterly_Data!$J$5:$J$114,"<>")
A13: >15% | B13: =COUNTIFS(Quarterly_Data!$H$5:$H$114,B$5,Quarterly_Data!$M$5:$M$114,$A13,Quarterly_Data!$J$5:$J$114,"<>") | C13: =COUNTIFS(Quarterly_Data!$H$5:$H$114,C$5,Quarterly_Data!$M$5:$M$114,$A13,Quarterly_Data!$J$5:$J$114,"<>") | D13: =COUNTIFS(Quarterly_Data!$H$5:$H$114,D$5,Quarterly_Data!$M$5:$M$114,$A13,Quarterly_Data!$J$5:$J$114,"<>") | E13: =COUNTIFS(Quarterly_Data!$H$5:$H$114,E$5,Quarterly_Data!$M$5:$M$114,$A13,Quarterly_Data!$J$5:$J$114,"<>") | F13: =COUNTIFS(Quarterly_Data!$H$5:$H$114,F$5,Quarterly_Data!$M$5:$M$114,$A13,Quarterly_Data!$J$5:$J$114,"<>")
A14: 5-YEAR FORWARD CAGR — AVERAGE
A15: EPS Growth | B15: Q1 Cheapest | C15: Q2 | D15: Q3 | E15: Q4 | F15: Q5 Most Expensive
A16: <5% | B16: =IFERROR(AVERAGEIFS(Quarterly_Data!$K$5:$K$114,Quarterly_Data!$H$5:$H$114,B$15,Quarterly_Data!$M$5:$M$114,$A16),"") | C16: =IFERROR(AVERAGEIFS(Quarterly_Data!$K$5:$K$114,Quarterly_Data!$H$5:$H$114,C$15,Quarterly_Data!$M$5:$M$114,$A16),"") | D16: =IFERROR(AVERAGEIFS(Quarterly_Data!$K$5:$K$114,Quarterly_Data!$H$5:$H$114,D$15,Quarterly_Data!$M$5:$M$114,$A16),"") | E16: =IFERROR(AVERAGEIFS(Quarterly_Data!$K$5:$K$114,Quarterly_Data!$H$5:$H$114,E$15,Quarterly_Data!$M$5:$M$114,$A16),"") | F16: =IFERROR(AVERAGEIFS(Quarterly_Data!$K$5:$K$114,Quarterly_Data!$H$5:$H$114,F$15,Quarterly_Data!$M$5:$M$114,$A16),"")
A17: 5-15% | B17: =IFERROR(AVERAGEIFS(Quarterly_Data!$K$5:$K$114,Quarterly_Data!$H$5:$H$114,B$15,Quarterly_Data!$M$5:$M$114,$A17),"") | C17: =IFERROR(AVERAGEIFS(Quarterly_Data!$K$5:$K$114,Quarterly_Data!$H$5:$H$114,C$15,Quarterly_Data!$M$5:$M$114,$A17),"") | D17: =IFERROR(AVERAGEIFS(Quarterly_Data!$K$5:$K$114,Quarterly_Data!$H$5:$H$114,D$15,Quarterly_Data!$M$5:$M$114,$A17),"") | E17: =IFERROR(AVERAGEIFS(Quarterly_Data!$K$5:$K$114,Quarterly_Data!$H$5:$H$114,E$15,Quarterly_Data!$M$5:$M$114,$A17),"") | F17: =IFERROR(AVERAGEIFS(Quarterly_Data!$K$5:$K$114,Quarterly_Data!$H$5:$H$114,F$15,Quarterly_Data!$M$5:$M$114,$A17),"")
A18: >15% | B18: =IFERROR(AVERAGEIFS(Quarterly_Data!$K$5:$K$114,Quarterly_Data!$H$5:$H$114,B$15,Quarterly_Data!$M$5:$M$114,$A18),"") | C18: =IFERROR(AVERAGEIFS(Quarterly_Data!$K$5:$K$114,Quarterly_Data!$H$5:$H$114,C$15,Quarterly_Data!$M$5:$M$114,$A18),"") | D18: =IFERROR(AVERAGEIFS(Quarterly_Data!$K$5:$K$114,Quarterly_Data!$H$5:$H$114,D$15,Quarterly_Data!$M$5:$M$114,$A18),"") | E18: =IFERROR(AVERAGEIFS(Quarterly_Data!$K$5:$K$114,Quarterly_Data!$H$5:$H$114,E$15,Quarterly_Data!$M$5:$M$114,$A18),"") | F18: =IFERROR(AVERAGEIFS(Quarterly_Data!$K$5:$K$114,Quarterly_Data!$H$5:$H$114,F$15,Quarterly_Data!$M$5:$M$114,$A18),"")
A20: Observation count (N)
A21: <5% | B21: =COUNTIFS(Quarterly_Data!$H$5:$H$114,B$15,Quarterly_Data!$M$5:$M$114,$A21,Quarterly_Data!$K$5:$K$114,"<>") | C21: =COUNTIFS(Quarterly_Data!$H$5:$H$114,C$15,Quarterly_Data!$M$5:$M$114,$A21,Quarterly_Data!$K$5:$K$114,"<>") | D21: =COUNTIFS(Quarterly_Data!$H$5:$H$114,D$15,Quarterly_Data!$M$5:$M$114,$A21,Quarterly_Data!$K$5:$K$114,"<>") | E21: =COUNTIFS(Quarterly_Data!$H$5:$H$114,E$15,Quarterly_Data!$M$5:$M$114,$A21,Quarterly_Data!$K$5:$K$114,"<>") | F21: =COUNTIFS(Quarterly_Data!$H$5:$H$114,F$15,Quarterly_Data!$M$5:$M$114,$A21,Quarterly_Data!$K$5:$K$114,"<>")
A22: 5-15% | B22: =COUNTIFS(Quarterly_Data!$H$5:$H$114,B$15,Quarterly_Data!$M$5:$M$114,$A22,Quarterly_Data!$K$5:$K$114,"<>") | C22: =COUNTIFS(Quarterly_Data!$H$5:$H$114,C$15,Quarterly_Data!$M$5:$M$114,$A22,Quarterly_Data!$K$5:$K$114,"<>") | D22: =COUNTIFS(Quarterly_Data!$H$5:$H$114,D$15,Quarterly_Data!$M$5:$M$114,$A22,Quarterly_Data!$K$5:$K$114,"<>") | E22: =COUNTIFS(Quarterly_Data!$H$5:$H$114,E$15,Quarterly_Data!$M$5:$M$114,$A22,Quarterly_Data!$K$5:$K$114,"<>") | F22: =COUNTIFS(Quarterly_Data!$H$5:$H$114,F$15,Quarterly_Data!$M$5:$M$114,$A22,Quarterly_Data!$K$5:$K$114,"<>")
A23: >15% | B23: =COUNTIFS(Quarterly_Data!$H$5:$H$114,B$15,Quarterly_Data!$M$5:$M$114,$A23,Quarterly_Data!$K$5:$K$114,"<>") | C23: =COUNTIFS(Quarterly_Data!$H$5:$H$114,C$15,Quarterly_Data!$M$5:$M$114,$A23,Quarterly_Data!$K$5:$K$114,"<>") | D23: =COUNTIFS(Quarterly_Data!$H$5:$H$114,D$15,Quarterly_Data!$M$5:$M$114,$A23,Quarterly_Data!$K$5:$K$114,"<>") | E23: =COUNTIFS(Quarterly_Data!$H$5:$H$114,E$15,Quarterly_Data!$M$5:$M$114,$A23,Quarterly_Data!$K$5:$K$114,"<>") | F23: =COUNTIFS(Quarterly_Data!$H$5:$H$114,F$15,Quarterly_Data!$M$5:$M$114,$A23,Quarterly_Data!$K$5:$K$114,"<>")

Sheet Signal_Backtest
A1: Backtest of Transparent BUY / HOLD / SELL Rule
A2: No-lookahead expanding P/E percentile within each regime. The rule uses 70% valuation score + 30% YoY implied EPS-growth score. Results are descriptive, not a guarantee.
A4: FORWARD RETURNS BY HISTORICAL SIGNAL
A5: Signal | B5: 1Y N | C5: 1Y Avg | D5: 1Y Loss % | E5: 3Y N | F5: 3Y CAGR Avg | G5: 3Y Loss % | H5: 5Y N | I5: 5Y CAGR Avg | J5: 5Y Loss %
A6: BUY | B6: =COUNTIFS(Quarterly_Data!$R$5:$R$114,$A6,Quarterly_Data!$I$5:$I$114,"<>") | C6: =IFERROR(AVERAGEIFS(Quarterly_Data!$I$5:$I$114,Quarterly_Data!$R$5:$R$114,$A6),"") | D6: =IFERROR(COUNTIFS(Quarterly_Data!$R$5:$R$114,$A6,Quarterly_Data!$I$5:$I$114,"<0")/B6,"") | E6: =COUNTIFS(Quarterly_Data!$R$5:$R$114,$A6,Quarterly_Data!$J$5:$J$114,"<>") | F6: =IFERROR(AVERAGEIFS(Quarterly_Data!$J$5:$J$114,Quarterly_Data!$R$5:$R$114,$A6),"") | G6: =IFERROR(COUNTIFS(Quarterly_Data!$R$5:$R$114,$A6,Quarterly_Data!$J$5:$J$114,"<0")/E6,"") | H6: =COUNTIFS(Quarterly_Data!$R$5:$R$114,$A6,Quarterly_Data!$K$5:$K$114,"<>") | I6: =IFERROR(AVERAGEIFS(Quarterly_Data!$K$5:$K$114,Quarterly_Data!$R$5:$R$114,$A6),"") | J6: =IFERROR(COUNTIFS(Quarterly_Data!$R$5:$R$114,$A6,Quarterly_Data!$K$5:$K$114,"<0")/H6,"")
A7: HOLD | B7: =COUNTIFS(Quarterly_Data!$R$5:$R$114,$A7,Quarterly_Data!$I$5:$I$114,"<>") | C7: =IFERROR(AVERAGEIFS(Quarterly_Data!$I$5:$I$114,Quarterly_Data!$R$5:$R$114,$A7),"") | D7: =IFERROR(COUNTIFS(Quarterly_Data!$R$5:$R$114,$A7,Quarterly_Data!$I$5:$I$114,"<0")/B7,"") | E7: =COUNTIFS(Quarterly_Data!$R$5:$R$114,$A7,Quarterly_Data!$J$5:$J$114,"<>") | F7: =IFERROR(AVERAGEIFS(Quarterly_Data!$J$5:$J$114,Quarterly_Data!$R$5:$R$114,$A7),"") | G7: =IFERROR(COUNTIFS(Quarterly_Data!$R$5:$R$114,$A7,Quarterly_Data!$J$5:$J$114,"<0")/E7,"") | H7: =COUNTIFS(Quarterly_Data!$R$5:$R$114,$A7,Quarterly_Data!$K$5:$K$114,"<>") | I7: =IFERROR(AVERAGEIFS(Quarterly_Data!$K$5:$K$114,Quarterly_Data!$R$5:$R$114,$A7),"") | J7: =IFERROR(COUNTIFS(Quarterly_Data!$R$5:$R$114,$A7,Quarterly_Data!$K$5:$K$114,"<0")/H7,"")
A8: SELL | B8: =COUNTIFS(Quarterly_Data!$R$5:$R$114,$A8,Quarterly_Data!$I$5:$I$114,"<>") | C8: =IFERROR(AVERAGEIFS(Quarterly_Data!$I$5:$I$114,Quarterly_Data!$R$5:$R$114,$A8),"") | D8: =IFERROR(COUNTIFS(Quarterly_Data!$R$5:$R$114,$A8,Quarterly_Data!$I$5:$I$114,"<0")/B8,"") | E8: =COUNTIFS(Quarterly_Data!$R$5:$R$114,$A8,Quarterly_Data!$J$5:$J$114,"<>") | F8: =IFERROR(AVERAGEIFS(Quarterly_Data!$J$5:$J$114,Quarterly_Data!$R$5:$R$114,$A8),"") | G8: =IFERROR(COUNTIFS(Quarterly_Data!$R$5:$R$114,$A8,Quarterly_Data!$J$5:$J$114,"<0")/E8,"") | H8: =COUNTIFS(Quarterly_Data!$R$5:$R$114,$A8,Quarterly_Data!$K$5:$K$114,"<>") | I8: =IFERROR(AVERAGEIFS(Quarterly_Data!$K$5:$K$114,Quarterly_Data!$R$5:$R$114,$A8),"") | J8: =IFERROR(COUNTIFS(Quarterly_Data!$R$5:$R$114,$A8,Quarterly_Data!$K$5:$K$114,"<0")/H8,"")
A11: RULE DEFINITION
A12: Valuation score | B12: 100 × (1 − expanding regime PE percentile)
A13: Growth score | B13: 20–100 piecewise score: ≤0% growth = 20; 5%=40; 10%=60; 15%=80; 25%+=100
A14: Composite | B14: 70% × Valuation Score + 30% × Growth Score
A15: BUY | B15: Composite ≥70
A16: HOLD | B16: 40–69.9
A17: SELL | B17: <40; interpreted as reduce/avoid fresh allocation, not shorting

Sheet Quarterly_Data
A1: NIFTY 50 Quarterly Backtest Data
A2: Quarter-end sampling reduces overlapping observations. Historical returns are NIFTY 50 Price Return Index returns (dividends excluded). Period-end labels represent month-end observations.
A4: Period End | B4: NIFTY 50 Close | C4: P/E (TTM) | D4: P/E Regime | E4: Implied EPS | F4: EPS Growth YoY | G4: Regime PE Percentile | H4: Valuation Quintile | I4: Fwd 1Y Return | J4: Fwd 3Y CAGR | K4: Fwd 5Y CAGR | L4: Fwd 10Y CAGR | M4: Growth Bucket | N4: Expanding PE Percentile | O4: Valuation Score | P4: Growth Score | Q4: Composite Score | R4: Signal
A5: 36250 | B5: 1078 | C5: 16.5 | D5: Standalone | E5: =IFERROR(B5/C5,"") | G5: =IFERROR((COUNTIF($C$5:$C$92,"<"&C5)+0.5*COUNTIF($C$5:$C$92,C5))/COUNT($C$5:$C$92),"") | H5: =IF(G5="","",IF(G5<=20%,"Q1 Cheapest",IF(G5<=40%,"Q2",IF(G5<=60%,"Q3",IF(G5<=80%,"Q4","Q5 Most Expensive"))))) | I5: =IFERROR(B9/B5-1,"") | J5: =IFERROR((B17/B5)^(1/3)-1,"") | K5: =IFERROR((B25/B5)^(1/5)-1,"") | L5: =IFERROR((B45/B5)^(1/10)-1,"") | M5: =IF(F5="","",IF(F5<5%,"<5%",IF(F5<15%,"5-15%",">15%"))) | N5: =IF(COUNT($C$5:C5)<8,"",(COUNTIF($C$5:C5,"<"&C5)+0.5*COUNTIF($C$5:C5,C5))/COUNT($C$5:C5)) | O5: =IF(N5="","",100*(1-N5)) | P5: =IF(F5="","",IF(F5<=0,20,IF(F5<5%,20+400*F5,IF(F5<10%,40+400*(F5-5%),IF(F5<15%,60+400*(F5-10%),IF(F5<25%,80+200*(F5-15%),100)))))) | Q5: =IF(OR(O5="",P5=""),"",70%*O5+30%*P5) | R5: =IF(Q5="","",IF(Q5>=70,"BUY",IF(Q5>=40,"HOLD","SELL")))
A6: 36341 | B6: 1187.7 | C6: 17.9 | D6: Standalone | E6: =IFERROR(B6/C6,"") | G6: =IFERROR((COUNTIF($C$5:$C$92,"<"&C6)+0.5*COUNTIF($C$5:$C$92,C6))/COUNT($C$5:$C$92),"") | H6: =IF(G6="","",IF(G6<=20%,"Q1 Cheapest",IF(G6<=40%,"Q2",IF(G6<=60%,"Q3",IF(G6<=80%,"Q4","Q5 Most Expensive"))))) | I6: =IFERROR(B10/B6-1,"") | J6: =IFERROR((B18/B6)^(1/3)-1,"") | K6: =IFERROR((B26/B6)^(1/5)-1,"") | L6: =IFERROR((B46/B6)^(1/10)-1,"") | M6: =IF(F6="","",IF(F6<5%,"<5%",IF(F6<15%,"5-15%",">15%"))) | N6: =IF(COUNT($C$5:C6)<8,"",(COUNTIF($C$5:C6,"<"&C6)+0.5*COUNTIF($C$5:C6,C6))/COUNT($C$5:C6)) | O6: =IF(N6="","",100*(1-N6)) | P6: =IF(F6="","",IF(F6<=0,20,IF(F6<5%,20+400*F6,IF(F6<10%,40+400*(F6-5%),IF(F6<15%,60+400*(F6-10%),IF(F6<25%,80+200*(F6-15%),100)))))) | Q6: =IF(OR(O6="",P6=""),"",70%*O6+30%*P6) | R6: =IF(Q6="","",IF(Q6>=70,"BUY",IF(Q6>=40,"HOLD","SELL")))
A7: 36433 | B7: 1413.1 | C7: 22 | D7: Standalone | E7: =IFERROR(B7/C7,"") | G7: =IFERROR((COUNTIF($C$5:$C$92,"<"&C7)+0.5*COUNTIF($C$5:$C$92,C7))/COUNT($C$5:$C$92),"") | H7: =IF(G7="","",IF(G7<=20%,"Q1 Cheapest",IF(G7<=40%,"Q2",IF(G7<=60%,"Q3",IF(G7<=80%,"Q4","Q5 Most Expensive"))))) | I7: =IFERROR(B11/B7-1,"") | J7: =IFERROR((B19/B7)^(1/3)-1,"") | K7: =IFERROR((B27/B7)^(1/5)-1,"") | L7: =IFERROR((B47/B7)^(1/10)-1,"") | M7: =IF(F7="","",IF(F7<5%,"<5%",IF(F7<15%,"5-15%",">15%"))) | N7: =IF(COUNT($C$5:C7)<8,"",(COUNTIF($C$5:C7,"<"&C7)+0.5*COUNTIF($C$5:C7,C7))/COUNT($C$5:C7)) | O7: =IF(N7="","",100*(1-N7)) | P7: =IF(F7="","",IF(F7<=0,20,IF(F7<5%,20+400*F7,IF(F7<10%,40+400*(F7-5%),IF(F7<15%,60+400*(F7-10%),IF(F7<25%,80+200*(F7-15%),100)))))) | Q7: =IF(OR(O7="",P7=""),"",70%*O7+30%*P7) | R7: =IF(Q7="","",IF(Q7>=70,"BUY",IF(Q7>=40,"HOLD","SELL")))
A8: 36525 | B8: 1480.4 | C8: 24.1 | D8: Standalone | E8: =IFERROR(B8/C8,"") | G8: =IFERROR((COUNTIF($C$5:$C$92,"<"&C8)+0.5*COUNTIF($C$5:$C$92,C8))/COUNT($C$5:$C$92),"") | H8: =IF(G8="","",IF(G8<=20%,"Q1 Cheapest",IF(G8<=40%,"Q2",IF(G8<=60%,"Q3",IF(G8<=80%,"Q4","Q5 Most Expensive"))))) | I8: =IFERROR(B12/B8-1,"") | J8: =IFERROR((B20/B8)^(1/3)-1,"") | K8: =IFERROR((B28/B8)^(1/5)-1,"") | L8: =IFERROR((B48/B8)^(1/10)-1,"") | M8: =IF(F8="","",IF(F8<5%,"<5%",IF(F8<15%,"5-15%",">15%"))) | N8: =IF(COUNT($C$5:C8)<8,"",(COUNTIF($C$5:C8,"<"&C8)+0.5*COUNTIF($C$5:C8,C8))/COUNT($C$5:C8)) | O8: =IF(N8="","",100*(1-N8)) | P8: =IF(F8="","",IF(F8<=0,20,IF(F8<5%,20+400*F8,IF(F8<10%,40+400*(F8-5%),IF(F8<15%,60+400*(F8-10%),IF(F8<25%,80+200*(F8-15%),100)))))) | Q8: =IF(OR(O8="",P8=""),"",70%*O8+30%*P8) | R8: =IF(Q8="","",IF(Q8>=70,"BUY",IF(Q8>=40,"HOLD","SELL")))
A9: 36616 | B9: 1528.4 | C9: 24.6 | D9: Standalone | E9: =IFERROR(B9/C9,"") | F9: =IF(D9=D5,IFERROR(E9/E5-1,""),"") | G9: =IFERROR((COUNTIF($C$5:$C$92,"<"&C9)+0.5*COUNTIF($C$5:$C$92,C9))/COUNT($C$5:$C$92),"") | H9: =IF(G9="","",IF(G9<=20%,"Q1 Cheapest",IF(G9<=40%,"Q2",IF(G9<=60%,"Q3",IF(G9<=80%,"Q4","Q5 Most Expensive"))))) | I9: =IFERROR(B13/B9-1,"") | J9: =IFERROR((B21/B9)^(1/3)-1,"") | K9: =IFERROR((B29/B9)^(1/5)-1,"") | L9: =IFERROR((B49/B9)^(1/10)-1,"") | M9: =IF(F9="","",IF(F9<5%,"<5%",IF(F9<15%,"5-15%",">15%"))) | N9: =IF(COUNT($C$5:C9)<8,"",(COUNTIF($C$5:C9,"<"&C9)+0.5*COUNTIF($C$5:C9,C9))/COUNT($C$5:C9)) | O9: =IF(N9="","",100*(1-N9)) | P9: =IF(F9="","",IF(F9<=0,20,IF(F9<5%,20+400*F9,IF(F9<10%,40+400*(F9-5%),IF(F9<15%,60+400*(F9-10%),IF(F9<25%,80+200*(F9-15%),100)))))) | Q9: =IF(OR(O9="",P9=""),"",70%*O9+30%*P9) | R9: =IF(Q9="","",IF(Q9>=70,"BUY",IF(Q9>=40,"HOLD","SELL")))
A10: 36707 | B10: 1471.4 | C10: 22.9 | D10: Standalone | E10: =IFERROR(B10/C10,"") | F10: =IF(D10=D6,IFERROR(E10/E6-1,""),"") | G10: =IFERROR((COUNTIF($C$5:$C$92,"<"&C10)+0.5*COUNTIF($C$5:$C$92,C10))/COUNT($C$5:$C$92),"") | H10: =IF(G10="","",IF(G10<=20%,"Q1 Cheapest",IF(G10<=40%,"Q2",IF(G10<=60%,"Q3",IF(G10<=80%,"Q4","Q5 Most Expensive"))))) | I10: =IFERROR(B14/B10-1,"") | J10: =IFERROR((B22/B10)^(1/3)-1,"") | K10: =IFERROR((B30/B10)^(1/5)-1,"") | L10: =IFERROR((B50/B10)^(1/10)-1,"") | M10: =IF(F10="","",IF(F10<5%,"<5%",IF(F10<15%,"5-15%",">15%"))) | N10: =IF(COUNT($C$5:C10)<8,"",(COUNTIF($C$5:C10,"<"&C10)+0.5*COUNTIF($C$5:C10,C10))/COUNT($C$5:C10)) | O10: =IF(N10="","",100*(1-N10)) | P10: =IF(F10="","",IF(F10<=0,20,IF(F10<5%,20+400*F10,IF(F10<10%,40+400*(F10-5%),IF(F10<15%,60+400*(F10-10%),IF(F10<25%,80+200*(F10-15%),100)))))) | Q10: =IF(OR(O10="",P10=""),"",70%*O10+30%*P10) | R10: =IF(Q10="","",IF(Q10>=70,"BUY",IF(Q10>=40,"HOLD","SELL")))
A11: 36799 | B11: 1271.6 | C11: 19.3 | D11: Standalone | E11: =IFERROR(B11/C11,"") | F11: =IF(D11=D7,IFERROR(E11/E7-1,""),"") | G11: =IFERROR((COUNTIF($C$5:$C$92,"<"&C11)+0.5*COUNTIF($C$5:$C$92,C11))/COUNT($C$5:$C$92),"") | H11: =IF(G11="","",IF(G11<=20%,"Q1 Cheapest",IF(G11<=40%,"Q2",IF(G11<=60%,"Q3",IF(G11<=80%,"Q4","Q5 Most Expensive"))))) | I11: =IFERROR(B15/B11-1,"") | J11: =IFERROR((B23/B11)^(1/3)-1,"") | K11: =IFERROR((B31/B11)^(1/5)-1,"") | L11: =IFERROR((B51/B11)^(1/10)-1,"") | M11: =IF(F11="","",IF(F11<5%,"<5%",IF(F11<15%,"5-15%",">15%"))) | N11: =IF(COUNT($C$5:C11)<8,"",(COUNTIF($C$5:C11,"<"&C11)+0.5*COUNTIF($C$5:C11,C11))/COUNT($C$5:C11)) | O11: =IF(N11="","",100*(1-N11)) | P11: =IF(F11="","",IF(F11<=0,20,IF(F11<5%,20+400*F11,IF(F11<10%,40+400*(F11-5%),IF(F11<15%,60+400*(F11-10%),IF(F11<25%,80+200*(F11-15%),100)))))) | Q11: =IF(OR(O11="",P11=""),"",70%*O11+30%*P11) | R11: =IF(Q11="","",IF(Q11>=70,"BUY",IF(Q11>=40,"HOLD","SELL")))
A12: 36891 | B12: 1263.5 | C12: 19.2 | D12: Standalone | E12: =IFERROR(B12/C12,"") | F12: =IF(D12=D8,IFERROR(E12/E8-1,""),"") | G12: =IFERROR((COUNTIF($C$5:$C$92,"<"&C12)+0.5*COUNTIF($C$5:$C$92,C12))/COUNT($C$5:$C$92),"") | H12: =IF(G12="","",IF(G12<=20%,"Q1 Cheapest",IF(G12<=40%,"Q2",IF(G12<=60%,"Q3",IF(G12<=80%,"Q4","Q5 Most Expensive"))))) | I12: =IFERROR(B16/B12-1,"") | J12: =IFERROR((B24/B12)^(1/3)-1,"") | K12: =IFERROR((B32/B12)^(1/5)-1,"") | L12: =IFERROR((B52/B12)^(1/10)-1,"") | M12: =IF(F12="","",IF(F12<5%,"<5%",IF(F12<15%,"5-15%",">15%"))) | N12: =IF(COUNT($C$5:C12)<8,"",(COUNTIF($C$5:C12,"<"&C12)+0.5*COUNTIF($C$5:C12,C12))/COUNT($C$5:C12)) | O12: =IF(N12="","",100*(1-N12)) | P12: =IF(F12="","",IF(F12<=0,20,IF(F12<5%,20+400*F12,IF(F12<10%,40+400*(F12-5%),IF(F12<15%,60+400*(F12-10%),IF(F12<25%,80+200*(F12-15%),100)))))) | Q12: =IF(OR(O12="",P12=""),"",70%*O12+30%*P12) | R12: =IF(Q12="","",IF(Q12>=70,"BUY",IF(Q12>=40,"HOLD","SELL")))
A13: 36981 | B13: 1148.2 | C13: 17.2 | D13: Standalone | E13: =IFERROR(B13/C13,"") | F13: =IF(D13=D9,IFERROR(E13/E9-1,""),"") | G13: =IFERROR((COUNTIF($C$5:$C$92,"<"&C13)+0.5*COUNTIF($C$5:$C$92,C13))/COUNT($C$5:$C$92),"") | H13: =IF(G13="","",IF(G13<=20%,"Q1 Cheapest",IF(G13<=40%,"Q2",IF(G13<=60%,"Q3",IF(G13<=80%,"Q4","Q5 Most Expensive"))))) | I13: =IFERROR(B17/B13-1,"") | J13: =IFERROR((B25/B13)^(1/3)-1,"") | K13: =IFERROR((B33/B13)^(1/5)-1,"") | L13: =IFERROR((B53/B13)^(1/10)-1,"") | M13: =IF(F13="","",IF(F13<5%,"<5%",IF(F13<15%,"5-15%",">15%"))) | N13: =IF(COUNT($C$5:C13)<8,"",(COUNTIF($C$5:C13,"<"&C13)+0.5*COUNTIF($C$5:C13,C13))/COUNT($C$5:C13)) | O13: =IF(N13="","",100*(1-N13)) | P13: =IF(F13="","",IF(F13<=0,20,IF(F13<5%,20+400*F13,IF(F13<10%,40+400*(F13-5%),IF(F13<15%,60+400*(F13-10%),IF(F13<25%,80+200*(F13-15%),100)))))) | Q13: =IF(OR(O13="",P13=""),"",70%*O13+30%*P13) | R13: =IF(Q13="","",IF(Q13>=70,"BUY",IF(Q13>=40,"HOLD","SELL")))
A14: 37072 | B14: 1107.9 | C14: 15.8 | D14: Standalone | E14: =IFERROR(B14/C14,"") | F14: =IF(D14=D10,IFERROR(E14/E10-1,""),"") | G14: =IFERROR((COUNTIF($C$5:$C$92,"<"&C14)+0.5*COUNTIF($C$5:$C$92,C14))/COUNT($C$5:$C$92),"") | H14: =IF(G14="","",IF(G14<=20%,"Q1 Cheapest",IF(G14<=40%,"Q2",IF(G14<=60%,"Q3",IF(G14<=80%,"Q4","Q5 Most Expensive"))))) | I14: =IFERROR(B18/B14-1,"") | J14: =IFERROR((B26/B14)^(1/3)-1,"") | K14: =IFERROR((B34/B14)^(1/5)-1,"") | L14: =IFERROR((B54/B14)^(1/10)-1,"") | M14: =IF(F14="","",IF(F14<5%,"<5%",IF(F14<15%,"5-15%",">15%"))) | N14: =IF(COUNT($C$5:C14)<8,"",(COUNTIF($C$5:C14,"<"&C14)+0.5*COUNTIF($C$5:C14,C14))/COUNT($C$5:C14)) | O14: =IF(N14="","",100*(1-N14)) | P14: =IF(F14="","",IF(F14<=0,20,IF(F14<5%,20+400*F14,IF(F14<10%,40+400*(F14-5%),IF(F14<15%,60+400*(F14-10%),IF(F14<25%,80+200*(F14-15%),100)))))) | Q14: =IF(OR(O14="",P14=""),"",70%*O14+30%*P14) | R14: =IF(Q14="","",IF(Q14>=70,"BUY",IF(Q14>=40,"HOLD","SELL")))
A15: 37164 | B15: 913.85 | C15: 13.2 | D15: Standalone | E15: =IFERROR(B15/C15,"") | F15: =IF(D15=D11,IFERROR(E15/E11-1,""),"") | G15: =IFERROR((COUNTIF($C$5:$C$92,"<"&C15)+0.5*COUNTIF($C$5:$C$92,C15))/COUNT($C$5:$C$92),"") | H15: =IF(G15="","",IF(G15<=20%,"Q1 Cheapest",IF(G15<=40%,"Q2",IF(G15<=60%,"Q3",IF(G15<=80%,"Q4","Q5 Most Expensive"))))) | I15: =IFERROR(B19/B15-1,"") | J15: =IFERROR((B27/B15)^(1/3)-1,"") | K15: =IFERROR((B35/B15)^(1/5)-1,"") | L15: =IFERROR((B55/B15)^(1/10)-1,"") | M15: =IF(F15="","",IF(F15<5%,"<5%",IF(F15<15%,"5-15%",">15%"))) | N15: =IF(COUNT($C$5:C15)<8,"",(COUNTIF($C$5:C15,"<"&C15)+0.5*COUNTIF($C$5:C15,C15))/COUNT($C$5:C15)) | O15: =IF(N15="","",100*(1-N15)) | P15: =IF(F15="","",IF(F15<=0,20,IF(F15<5%,20+400*F15,IF(F15<10%,40+400*(F15-5%),IF(F15<15%,60+400*(F15-10%),IF(F15<25%,80+200*(F15-15%),100)))))) | Q15: =IF(OR(O15="",P15=""),"",70%*O15+30%*P15) | R15: =IF(Q15="","",IF(Q15>=70,"BUY",IF(Q15>=40,"HOLD","SELL")))
A16: 37256 | B16: 1059 | C16: 15.3 | D16: Standalone | E16: =IFERROR(B16/C16,"") | F16: =IF(D16=D12,IFERROR(E16/E12-1,""),"") | G16: =IFERROR((COUNTIF($C$5:$C$92,"<"&C16)+0.5*COUNTIF($C$5:$C$92,C16))/COUNT($C$5:$C$92),"") | H16: =IF(G16="","",IF(G16<=20%,"Q1 Cheapest",IF(G16<=40%,"Q2",IF(G16<=60%,"Q3",IF(G16<=80%,"Q4","Q5 Most Expensive"))))) | I16: =IFERROR(B20/B16-1,"") | J16: =IFERROR((B28/B16)^(1/3)-1,"") | K16: =IFERROR((B36/B16)^(1/5)-1,"") | L16: =IFERROR((B56/B16)^(1/10)-1,"") | M16: =IF(F16="","",IF(F16<5%,"<5%",IF(F16<15%,"5-15%",">15%"))) | N16: =IF(COUNT($C$5:C16)<8,"",(COUNTIF($C$5:C16,"<"&C16)+0.5*COUNTIF($C$5:C16,C16))/COUNT($C$5:C16)) | O16: =IF(N16="","",100*(1-N16)) | P16: =IF(F16="","",IF(F16<=0,20,IF(F16<5%,20+400*F16,IF(F16<10%,40+400*(F16-5%),IF(F16<15%,60+400*(F16-10%),IF(F16<25%,80+200*(F16-15%),100)))))) | Q16: =IF(OR(O16="",P16=""),"",70%*O16+30%*P16) | R16: =IF(Q16="","",IF(Q16>=70,"BUY",IF(Q16>=40,"HOLD","SELL")))
A17: 37346 | B17: 1129.5 | C17: 18.1 | D17: Standalone | E17: =IFERROR(B17/C17,"") | F17: =IF(D17=D13,IFERROR(E17/E13-1,""),"") | G17: =IFERROR((COUNTIF($C$5:$C$92,"<"&C17)+0.5*COUNTIF($C$5:$C$92,C17))/COUNT($C$5:$C$92),"") | H17: =IF(G17="","",IF(G17<=20%,"Q1 Cheapest",IF(G17<=40%,"Q2",IF(G17<=60%,"Q3",IF(G17<=80%,"Q4","Q5 Most Expensive"))))) | I17: =IFERROR(B21/B17-1,"") | J17: =IFERROR((B29/B17)^(1/3)-1,"") | K17: =IFERROR((B37/B17)^(1/5)-1,"") | L17: =IFERROR((B57/B17)^(1/10)-1,"") | M17: =IF(F17="","",IF(F17<5%,"<5%",IF(F17<15%,"5-15%",">15%"))) | N17: =IF(COUNT($C$5:C17)<8,"",(COUNTIF($C$5:C17,"<"&C17)+0.5*COUNTIF($C$5:C17,C17))/COUNT($C$5:C17)) | O17: =IF(N17="","",100*(1-N17)) | P17: =IF(F17="","",IF(F17<=0,20,IF(F17<5%,20+400*F17,IF(F17<10%,40+400*(F17-5%),IF(F17<15%,60+400*(F17-10%),IF(F17<25%,80+200*(F17-15%),100)))))) | Q17: =IF(OR(O17="",P17=""),"",70%*O17+30%*P17) | R17: =IF(Q17="","",IF(Q17>=70,"BUY",IF(Q17>=40,"HOLD","SELL")))
A18: 37437 | B18: 1057.8 | C18: 15.7 | D18: Standalone | E18: =IFERROR(B18/C18,"") | F18: =IF(D18=D14,IFERROR(E18/E14-1,""),"") | G18: =IFERROR((COUNTIF($C$5:$C$92,"<"&C18)+0.5*COUNTIF($C$5:$C$92,C18))/COUNT($C$5:$C$92),"") | H18: =IF(G18="","",IF(G18<=20%,"Q1 Cheapest",IF(G18<=40%,"Q2",IF(G18<=60%,"Q3",IF(G18<=80%,"Q4","Q5 Most Expensive"))))) | I18: =IFERROR(B22/B18-1,"") | J18: =IFERROR((B30/B18)^(1/3)-1,"") | K18: =IFERROR((B38/B18)^(1/5)-1,"") | L18: =IFERROR((B58/B18)^(1/10)-1,"") | M18: =IF(F18="","",IF(F18<5%,"<5%",IF(F18<15%,"5-15%",">15%"))) | N18: =IF(COUNT($C$5:C18)<8,"",(COUNTIF($C$5:C18,"<"&C18)+0.5*COUNTIF($C$5:C18,C18))/COUNT($C$5:C18)) | O18: =IF(N18="","",100*(1-N18)) | P18: =IF(F18="","",IF(F18<=0,20,IF(F18<5%,20+400*F18,IF(F18<10%,40+400*(F18-5%),IF(F18<15%,60+400*(F18-10%),IF(F18<25%,80+200*(F18-15%),100)))))) | Q18: =IF(OR(O18="",P18=""),"",70%*O18+30%*P18) | R18: =IF(Q18="","",IF(Q18>=70,"BUY",IF(Q18>=40,"HOLD","SELL")))
A19: 37529 | B19: 963.15 | C19: 14.3 | D19: Standalone | E19: =IFERROR(B19/C19,"") | F19: =IF(D19=D15,IFERROR(E19/E15-1,""),"") | G19: =IFERROR((COUNTIF($C$5:$C$92,"<"&C19)+0.5*COUNTIF($C$5:$C$92,C19))/COUNT($C$5:$C$92),"") | H19: =IF(G19="","",IF(G19<=20%,"Q1 Cheapest",IF(G19<=40%,"Q2",IF(G19<=60%,"Q3",IF(G19<=80%,"Q4","Q5 Most Expensive"))))) | I19: =IFERROR(B23/B19-1,"") | J19: =IFERROR((B31/B19)^(1/3)-1,"") | K19: =IFERROR((B39/B19)^(1/5)-1,"") | L19: =IFERROR((B59/B19)^(1/10)-1,"") | M19: =IF(F19="","",IF(F19<5%,"<5%",IF(F19<15%,"5-15%",">15%"))) | N19: =IF(COUNT($C$5:C19)<8,"",(COUNTIF($C$5:C19,"<"&C19)+0.5*COUNTIF($C$5:C19,C19))/COUNT($C$5:C19)) | O19: =IF(N19="","",100*(1-N19)) | P19: =IF(F19="","",IF(F19<=0,20,IF(F19<5%,20+400*F19,IF(F19<10%,40+400*(F19-5%),IF(F19<15%,60+400*(F19-10%),IF(F19<25%,80+200*(F19-15%),100)))))) | Q19: =IF(OR(O19="",P19=""),"",70%*O19+30%*P19) | R19: =IF(Q19="","",IF(Q19>=70,"BUY",IF(Q19>=40,"HOLD","SELL")))
A20: 37621 | B20: 1093.5 | C20: 14.8 | D20: Standalone | E20: =IFERROR(B20/C20,"") | F20: =IF(D20=D16,IFERROR(E20/E16-1,""),"") | G20: =IFERROR((COUNTIF($C$5:$C$92,"<"&C20)+0.5*COUNTIF($C$5:$C$92,C20))/COUNT($C$5:$C$92),"") | H20: =IF(G20="","",IF(G20<=20%,"Q1 Cheapest",IF(G20<=40%,"Q2",IF(G20<=60%,"Q3",IF(G20<=80%,"Q4","Q5 Most Expensive"))))) | I20: =IFERROR(B24/B20-1,"") | J20: =IFERROR((B32/B20)^(1/3)-1,"") | K20: =IFERROR((B40/B20)^(1/5)-1,"") | L20: =IFERROR((B60/B20)^(1/10)-1,"") | M20: =IF(F20="","",IF(F20<5%,"<5%",IF(F20<15%,"5-15%",">15%"))) | N20: =IF(COUNT($C$5:C20)<8,"",(COUNTIF($C$5:C20,"<"&C20)+0.5*COUNTIF($C$5:C20,C20))/COUNT($C$5:C20)) | O20: =IF(N20="","",100*(1-N20)) | P20: =IF(F20="","",IF(F20<=0,20,IF(F20<5%,20+400*F20,IF(F20<10%,40+400*(F20-5%),IF(F20<15%,60+400*(F20-10%),IF(F20<25%,80+200*(F20-15%),100)))))) | Q20: =IF(OR(O20="",P20=""),"",70%*O20+30%*P20) | R20: =IF(Q20="","",IF(Q20>=70,"BUY",IF(Q20>=40,"HOLD","SELL")))
... A74: 42551 | B74: 8287.7 | C74: 22.8 | D74: Standalone | E74: =IFERROR(B74/C74,"") | F74: =IF(D74=D70,IFERROR(E74/E70-1,""),"") | G74: =IFERROR((COUNTIF($C$5:$C$92,"<"&C74)+0.5*COUNTIF($C$5:$C$92,C74))/COUNT($C$5:$C$92),"") | H74: =IF(G74="","",IF(G74<=20%,"Q1 Cheapest",IF(G74<=40%,"Q2",IF(G74<=60%,"Q3",IF(G74<=80%,"Q4","Q5 Most Expensive"))))) | I74: =IFERROR(B78/B74-1,"") | J74: =IFERROR((B86/B74)^(1/3)-1,"") | K74: =IFERROR((B94/B74)^(1/5)-1,"") | L74: =IFERROR((B114/B74)^(1/10)-1,"") | M74: =IF(F74="","",IF(F74<5%,"<5%",IF(F74<15%,"5-15%",">15%"))) | N74: =IF(COUNT($C$5:C74)<8,"",(COUNTIF($C$5:C74,"<"&C74)+0.5*COUNTIF($C$5:C74,C74))/COUNT($C$5:C74)) | O74: =IF(N74="","",100*(1-N74)) | P74: =IF(F74="","",IF(F74<=0,20,IF(F74<5%,20+400*F74,IF(F74<10%,40+400*(F74-5%),IF(F74<15%,60+400*(F74-10%),IF(F74<25%,80+200*(F74-15%),100)))))) | Q74: =IF(OR(O74="",P74=""),"",70%*O74+30%*P74) | R74: =IF(Q74="","",IF(Q74>=70,"BUY",IF(Q74>=40,"HOLD","SELL")))
A75: 42643 | B75: 8611.1 | C75: 23.4 | D75: Standalone | E75: =IFERROR(B75/C75,"") | F75: =IF(D75=D71,IFERROR(E75/E71-1,""),"") | G75: =IFERROR((COUNTIF($C$5:$C$92,"<"&C75)+0.5*COUNTIF($C$5:$C$92,C75))/COUNT($C$5:$C$92),"") | H75: =IF(G75="","",IF(G75<=20%,"Q1 Cheapest",IF(G75<=40%,"Q2",IF(G75<=60%,"Q3",IF(G75<=80%,"Q4","Q5 Most Expensive"))))) | I75: =IFERROR(B79/B75-1,"") | J75: =IFERROR((B87/B75)^(1/3)-1,"") | K75: =IFERROR((B95/B75)^(1/5)-1,"") | M75: =IF(F75="","",IF(F75<5%,"<5%",IF(F75<15%,"5-15%",">15%"))) | N75: =IF(COUNT($C$5:C75)<8,"",(COUNTIF($C$5:C75,"<"&C75)+0.5*COUNTIF($C$5:C75,C75))/COUNT($C$5:C75)) | O75: =IF(N75="","",100*(1-N75)) | P75: =IF(F75="","",IF(F75<=0,20,IF(F75<5%,20+400*F75,IF(F75<10%,40+400*(F75-5%),IF(F75<15%,60+400*(F75-10%),IF(F75<25%,80+200*(F75-15%),100)))))) | Q75: =IF(OR(O75="",P75=""),"",70%*O75+30%*P75) | R75: =IF(Q75="","",IF(Q75>=70,"BUY",IF(Q75>=40,"HOLD","SELL")))
A76: 42735 | B76: 8185.8 | C76: 21.9 | D76: Standalone | E76: =IFERROR(B76/C76,"") | F76: =IF(D76=D72,IFERROR(E76/E72-1,""),"") | G76: =IFERROR((COUNTIF($C$5:$C$92,"<"&C76)+0.5*COUNTIF($C$5:$C$92,C76))/COUNT($C$5:$C$92),"") | H76: =IF(G76="","",IF(G76<=20%,"Q1 Cheapest",IF(G76<=40%,"Q2",IF(G76<=60%,"Q3",IF(G76<=80%,"Q4","Q5 Most Expensive"))))) | I76: =IFERROR(B80/B76-1,"") | J76: =IFERROR((B88/B76)^(1/3)-1,"") | K76: =IFERROR((B96/B76)^(1/5)-1,"") | M76: =IF(F76="","",IF(F76<5%,"<5%",IF(F76<15%,"5-15%",">15%"))) | N76: =IF(COUNT($C$5:C76)<8,"",(COUNTIF($C$5:C76,"<"&C76)+0.5*COUNTIF($C$5:C76,C76))/COUNT($C$5:C76)) | O76: =IF(N76="","",100*(1-N76)) | P76: =IF(F76="","",IF(F76<=0,20,IF(F76<5%,20+400*F76,IF(F76<10%,40+400*(F76-5%),IF(F76<15%,60+400*(F76-10%),IF(F76<25%,80+200*(F76-15%),100)))))) | Q76: =IF(OR(O76="",P76=""),"",70%*O76+30%*P76) | R76: =IF(Q76="","",IF(Q76>=70,"BUY",IF(Q76>=40,"HOLD","SELL")))
A77: 42825 | B77: 9173.7 | C77: 23.3 | D77: Standalone | E77: =IFERROR(B77/C77,"") | F77: =IF(D77=D73,IFERROR(E77/E73-1,""),"") | G77: =IFERROR((COUNTIF($C$5:$C$92,"<"&C77)+0.5*COUNTIF($C$5:$C$92,C77))/COUNT($C$5:$C$92),"") | H77: =IF(G77="","",IF(G77<=20%,"Q1 Cheapest",IF(G77<=40%,"Q2",IF(G77<=60%,"Q3",IF(G77<=80%,"Q4","Q5 Most Expensive"))))) | I77: =IFERROR(B81/B77-1,"") | J77: =IFERROR((B89/B77)^(1/3)-1,"") | K77: =IFERROR((B97/B77)^(1/5)-1,"") | M77: =IF(F77="","",IF(F77<5%,"<5%",IF(F77<15%,"5-15%",">15%"))) | N77: =IF(COUNT($C$5:C77)<8,"",(COUNTIF($C$5:C77,"<"&C77)+0.5*COUNTIF($C$5:C77,C77))/COUNT($C$5:C77)) | O77: =IF(N77="","",100*(1-N77)) | P77: =IF(F77="","",IF(F77<=0,20,IF(F77<5%,20+400*F77,IF(F77<10%,40+400*(F77-5%),IF(F77<15%,60+400*(F77-10%),IF(F77<25%,80+200*(F77-15%),100)))))) | Q77: =IF(OR(O77="",P77=""),"",70%*O77+30%*P77) | R77: =IF(Q77="","",IF(Q77>=70,"BUY",IF(Q77>=40,"HOLD","SELL")))
A78: 42916 | B78: 9520.9 | C78: 24.2 | D78: Standalone | E78: =IFERROR(B78/C78,"") | F78: =IF(D78=D74,IFERROR(E78/E74-1,""),"") | G78: =IFERROR((COUNTIF($C$5:$C$92,"<"&C78)+0.5*COUNTIF($C$5:$C$92,C78))/COUNT($C$5:$C$92),"") | H78: =IF(G78="","",IF(G78<=20%,"Q1 Cheapest",IF(G78<=40%,"Q2",IF(G78<=60%,"Q3",IF(G78<=80%,"Q4","Q5 Most Expensive"))))) | I78: =IFERROR(B82/B78-1,"") | J78: =IFERROR((B90/B78)^(1/3)-1,"") | K78: =IFERROR((B98/B78)^(1/5)-1,"") | M78: =IF(F78="","",IF(F78<5%,"<5%",IF(F78<15%,"5-15%",">15%"))) | N78: =IF(COUNT($C$5:C78)<8,"",(COUNTIF($C$5:C78,"<"&C78)+0.5*COUNTIF($C$5:C78,C78))/COUNT($C$5:C78)) | O78: =IF(N78="","",100*(1-N78)) | P78: =IF(F78="","",IF(F78<=0,20,IF(F78<5%,20+400*F78,IF(F78<10%,40+400*(F78-5%),IF(F78<15%,60+400*(F78-10%),IF(F78<25%,80+200*(F78-15%),100)))))) | Q78: =IF(OR(O78="",P78=""),"",70%*O78+30%*P78) | R78: =IF(Q78="","",IF(Q78>=70,"BUY",IF(Q78>=40,"HOLD","SELL")))
A79: 43008 | B79: 9788.6 | C79: 25.4 | D79: Standalone | E79: =IFERROR(B79/C79,"") | F79: =IF(D79=D75,IFERROR(E79/E75-1,""),"") | G79: =IFERROR((COUNTIF($C$5:$C$92,"<"&C79)+0.5*COUNTIF($C$5:$C$92,C79))/COUNT($C$5:$C$92),"") | H79: =IF(G79="","",IF(G79<=20%,"Q1 Cheapest",IF(G79<=40%,"Q2",IF(G79<=60%,"Q3",IF(G79<=80%,"Q4","Q5 Most Expensive"))))) | I79: =IFERROR(B83/B79-1,"") | J79: =IFERROR((B91/B79)^(1/3)-1,"") | K79: =IFERROR((B99/B79)^(1/5)-1,"") | M79: =IF(F79="","",IF(F79<5%,"<5%",IF(F79<15%,"5-15%",">15%"))) | N79: =IF(COUNT($C$5:C79)<8,"",(COUNTIF($C$5:C79,"<"&C79)+0.5*COUNTIF($C$5:C79,C79))/COUNT($C$5:C79)) | O79: =IF(N79="","",100*(1-N79)) | P79: =IF(F79="","",IF(F79<=0,20,IF(F79<5%,20+400*F79,IF(F79<10%,40+400*(F79-5%),IF(F79<15%,60+400*(F79-10%),IF(F79<25%,80+200*(F79-15%),100)))))) | Q79: =IF(OR(O79="",P79=""),"",70%*O79+30%*P79) | R79: =IF(Q79="","",IF(Q79>=70,"BUY",IF(Q79>=40,"HOLD","SELL")))
A80: 43100 | B80: 10530 | C80: 26.9 | D80: Standalone | E80: =IFERROR(B80/C80,"") | F80: =IF(D80=D76,IFERROR(E80/E76-1,""),"") | G80: =IFERROR((COUNTIF($C$5:$C$92,"<"&C80)+0.5*COUNTIF($C$5:$C$92,C80))/COUNT($C$5:$C$92),"") | H80: =IF(G80="","",IF(G80<=20%,"Q1 Cheapest",IF(G80<=40%,"Q2",IF(G80<=60%,"Q3",IF(G80<=80%,"Q4","Q5 Most Expensive"))))) | I80: =IFERROR(B84/B80-1,"") | J80: =IFERROR((B92/B80)^(1/3)-1,"") | K80: =IFERROR((B100/B80)^(1/5)-1,"") | M80: =IF(F80="","",IF(F80<5%,"<5%",IF(F80<15%,"5-15%",">15%"))) | N80: =IF(COUNT($C$5:C80)<8,"",(COUNTIF($C$5:C80,"<"&C80)+0.5*COUNTIF($C$5:C80,C80))/COUNT($C$5:C80)) | O80: =IF(N80="","",100*(1-N80)) | P80: =IF(F80="","",IF(F80<=0,20,IF(F80<5%,20+400*F80,IF(F80<10%,40+400*(F80-5%),IF(F80<15%,60+400*(F80-10%),IF(F80<25%,80+200*(F80-15%),100)))))) | Q80: =IF(OR(O80="",P80=""),"",70%*O80+30%*P80) | R80: =IF(Q80="","",IF(Q80>=70,"BUY",IF(Q80>=40,"HOLD","SELL")))
A81: 43190 | B81: 10113.7 | C81: 24.7 | D81: Standalone | E81: =IFERROR(B81/C81,"") | F81: =IF(D81=D77,IFERROR(E81/E77-1,""),"") | G81: =IFERROR((COUNTIF($C$5:$C$92,"<"&C81)+0.5*COUNTIF($C$5:$C$92,C81))/COUNT($C$5:$C$92),"") | H81: =IF(G81="","",IF(G81<=20%,"Q1 Cheapest",IF(G81<=40%,"Q2",IF(G81<=60%,"Q3",IF(G81<=80%,"Q4","Q5 Most Expensive"))))) | I81: =IFERROR(B85/B81-1,"") | J81: =IFERROR((B93/B81)^(1/3)-1,"") | K81: =IFERROR((B101/B81)^(1/5)-1,"") | M81: =IF(F81="","",IF(F81<5%,"<5%",IF(F81<15%,"5-15%",">15%"))) | N81: =IF(COUNT($C$5:C81)<8,"",(COUNTIF($C$5:C81,"<"&C81)+0.5*COUNTIF($C$5:C81,C81))/COUNT($C$5:C81)) | O81: =IF(N81="","",100*(1-N81)) | P81: =IF(F81="","",IF(F81<=0,20,IF(F81<5%,20+400*F81,IF(F81<10%,40+400*(F81-5%),IF(F81<15%,60+400*(F81-10%),IF(F81<25%,80+200*(F81-15%),100)))))) | Q81: =IF(OR(O81="",P81=""),"",70%*O81+30%*P81) | R81: =IF(Q81="","",IF(Q81>=70,"BUY",IF(Q81>=40,"HOLD","SELL")))
A82: 43281 | B82: 10714.3 | C82: 25.9 | D82: Standalone | E82: =IFERROR(B82/C82,"") | F82: =IF(D82=D78,IFERROR(E82/E78-1,""),"") | G82: =IFERROR((COUNTIF($C$5:$C$92,"<"&C82)+0.5*COUNTIF($C$5:$C$92,C82))/COUNT($C$5:$C$92),"") | H82: =IF(G82="","",IF(G82<=20%,"Q1 Cheapest",IF(G82<=40%,"Q2",IF(G82<=60%,"Q3",IF(G82<=80%,"Q4","Q5 Most Expensive"))))) | I82: =IFERROR(B86/B82-1,"") | J82: =IFERROR((B94/B82)^(1/3)-1,"") | K82: =IFERROR((B102/B82)^(1/5)-1,"") | M82: =IF(F82="","",IF(F82<5%,"<5%",IF(F82<15%,"5-15%",">15%"))) | N82: =IF(COUNT($C$5:C82)<8,"",(COUNTIF($C$5:C82,"<"&C82)+0.5*COUNTIF($C$5:C82,C82))/COUNT($C$5:C82)) | O82: =IF(N82="","",100*(1-N82)) | P82: =IF(F82="","",IF(F82<=0,20,IF(F82<5%,20+400*F82,IF(F82<10%,40+400*(F82-5%),IF(F82<15%,60+400*(F82-10%),IF(F82<25%,80+200*(F82-15%),100)))))) | Q82: =IF(OR(O82="",P82=""),"",70%*O82+30%*P82) | R82: =IF(Q82="","",IF(Q82>=70,"BUY",IF(Q82>=40,"HOLD","SELL")))
A83: 43373 | B83: 10930.45 | C83: 26.4 | D83: Standalone | E83: =IFERROR(B83/C83,"") | F83: =IF(D83=D79,IFERROR(E83/E79-1,""),"") | G83: =IFERROR((COUNTIF($C$5:$C$92,"<"&C83)+0.5*COUNTIF($C$5:$C$92,C83))/COUNT($C$5:$C$92),"") | H83: =IF(G83="","",IF(G83<=20%,"Q1 Cheapest",IF(G83<=40%,"Q2",IF(G83<=60%,"Q3",IF(G83<=80%,"Q4","Q5 Most Expensive"))))) | I83: =IFERROR(B87/B83-1,"") | J83: =IFERROR((B95/B83)^(1/3)-1,"") | K83: =IFERROR((B103/B83)^(1/5)-1,"") | M83: =IF(F83="","",IF(F83<5%,"<5%",IF(F83<15%,"5-15%",">15%"))) | N83: =IF(COUNT($C$5:C83)<8,"",(COUNTIF($C$5:C83,"<"&C83)+0.5*COUNTIF($C$5:C83,C83))/COUNT($C$5:C83)) | O83: =IF(N83="","",100*(1-N83)) | P83: =IF(F83="","",IF(F83<=0,20,IF(F83<5%,20+400*F83,IF(F83<10%,40+400*(F83-5%),IF(F83<15%,60+400*(F83-10%),IF(F83<25%,80+200*(F83-15%),100)))))) | Q83: =IF(OR(O83="",P83=""),"",70%*O83+30%*P83) | R83: =IF(Q83="","",IF(Q83>=70,"BUY",IF(Q83>=40,"HOLD","SELL")))
A84: 43465 | B84: 10862.55 | C84: 26.2 | D84: Standalone | E84: =IFERROR(B84/C84,"") | F84: =IF(D84=D80,IFERROR(E84/E80-1,""),"") | G84: =IFERROR((COUNTIF($C$5:$C$92,"<"&C84)+0.5*COUNTIF($C$5:$C$92,C84))/COUNT($C$5:$C$92),"") | H84: =IF(G84="","",IF(G84<=20%,"Q1 Cheapest",IF(G84<=40%,"Q2",IF(G84<=60%,"Q3",IF(G84<=80%,"Q4","Q5 Most Expensive"))))) | I84: =IFERROR(B88/B84-1,"") | J84: =IFERROR((B96/B84)^(1/3)-1,"") | K84: =IFERROR((B104/B84)^(1/5)-1,"") | M84: =IF(F84="","",IF(F84<5%,"<5%",IF(F84<15%,"5-15%",">15%"))) | N84: =IF(COUNT($C$5:C84)<8,"",(COUNTIF($C$5:C84,"<"&C84)+0.5*COUNTIF($C$5:C84,C84))/COUNT($C$5:C84)) | O84: =IF(N84="","",100*(1-N84)) | P84: =IF(F84="","",IF(F84<=0,20,IF(F84<5%,20+400*F84,IF(F84<10%,40+400*(F84-5%),IF(F84<15%,60+400*(F84-10%),IF(F84<25%,80+200*(F84-15%),100)))))) | Q84: =IF(OR(O84="",P84=""),"",70%*O84+30%*P84) | R84: =IF(Q84="","",IF(Q84>=70,"BUY",IF(Q84>=40,"HOLD","SELL")))
A85: 43555 | B85: 11623.9 | C85: 29 | D85: Standalone | E85: =IFERROR(B85/C85,"") | F85: =IF(D85=D81,IFERROR(E85/E81-1,""),"") | G85: =IFERROR((COUNTIF($C$5:$C$92,"<"&C85)+0.5*COUNTIF($C$5:$C$92,C85))/COUNT($C$5:$C$92),"") | H85: =IF(G85="","",IF(G85<=20%,"Q1 Cheapest",IF(G85<=40%,"Q2",IF(G85<=60%,"Q3",IF(G85<=80%,"Q4","Q5 Most Expensive"))))) | I85: =IFERROR(B89/B85-1,"") | J85: =IFERROR((B97/B85)^(1/3)-1,"") | K85: =IFERROR((B105/B85)^(1/5)-1,"") | M85: =IF(F85="","",IF(F85<5%,"<5%",IF(F85<15%,"5-15%",">15%"))) | N85: =IF(COUNT($C$5:C85)<8,"",(COUNTIF($C$5:C85,"<"&C85)+0.5*COUNTIF($C$5:C85,C85))/COUNT($C$5:C85)) | O85: =IF(N85="","",100*(1-N85)) | P85: =IF(F85="","",IF(F85<=0,20,IF(F85<5%,20+400*F85,IF(F85<10%,40+400*(F85-5%),IF(F85<15%,60+400*(F85-10%),IF(F85<25%,80+200*(F85-15%),100)))))) | Q85: =IF(OR(O85="",P85=""),"",70%*O85+30%*P85) | R85: =IF(Q85="","",IF(Q85>=70,"BUY",IF(Q85>=40,"HOLD","SELL")))
A86: 43646 | B86: 11788.85 | C86: 29 | D86: Standalone | E86: =IFERROR(B86/C86,"") | F86: =IF(D86=D82,IFERROR(E86/E82-1,""),"") | G86: =IFERROR((COUNTIF($C$5:$C$92,"<"&C86)+0.5*COUNTIF($C$5:$C$92,C86))/COUNT($C$5:$C$92),"") | H86: =IF(G86="","",IF(G86<=20%,"Q1 Cheapest",IF(G86<=40%,"Q2",IF(G86<=60%,"Q3",IF(G86<=80%,"Q4","Q5 Most Expensive"))))) | I86: =IFERROR(B90/B86-1,"") | J86: =IFERROR((B98/B86)^(1/3)-1,"") | K86: =IFERROR((B106/B86)^(1/5)-1,"") | M86: =IF(F86="","",IF(F86<5%,"<5%",IF(F86<15%,"5-15%",">15%"))) | N86: =IF(COUNT($C$5:C86)<8,"",(COUNTIF($C$5:C86,"<"&C86)+0.5*COUNTIF($C$5:C86,C86))/COUNT($C$5:C86)) | O86: =IF(N86="","",100*(1-N86)) | P86: =IF(F86="","",IF(F86<=0,20,IF(F86<5%,20+400*F86,IF(F86<10%,40+400*(F86-5%),IF(F86<15%,60+400*(F86-10%),IF(F86<25%,80+200*(F86-15%),100)))))) | Q86: =IF(OR(O86="",P86=""),"",70%*O86+30%*P86) | R86: =IF(Q86="","",IF(Q86>=70,"BUY",IF(Q86>=40,"HOLD","SELL")))
... A92: 44196 | B92: 13981.75 | C92: 38.5 | D92: Standalone | E92: =IFERROR(B92/C92,"") | F92: =IF(D92=D88,IFERROR(E92/E88-1,""),"") | G92: =IFERROR((COUNTIF($C$5:$C$92,"<"&C92)+0.5*COUNTIF($C$5:$C$92,C92))/COUNT($C$5:$C$92),"") | H92: =IF(G92="","",IF(G92<=20%,"Q1 Cheapest",IF(G92<=40%,"Q2",IF(G92<=60%,"Q3",IF(G92<=80%,"Q4","Q5 Most Expensive"))))) | I92: =IFERROR(B96/B92-1,"") | J92: =IFERROR((B104/B92)^(1/3)-1,"") | K92: =IFERROR((B112/B92)^(1/5)-1,"") | M92: =IF(F92="","",IF(F92<5%,"<5%",IF(F92<15%,"5-15%",">15%"))) | N92: =IF(COUNT($C$5:C92)<8,"",(COUNTIF($C$5:C92,"<"&C92)+0.5*COUNTIF($C$5:C92,C92))/COUNT($C$5:C92)) | O92: =IF(N92="","",100*(1-N92)) | P92: =IF(F92="","",IF(F92<=0,20,IF(F92<5%,20+400*F92,IF(F92<10%,40+400*(F92-5%),IF(F92<15%,60+400*(F92-10%),IF(F92<25%,80+200*(F92-15%),100)))))) | Q92: =IF(OR(O92="",P92=""),"",70%*O92+30%*P92) | R92: =IF(Q92="","",IF(Q92>=70,"BUY",IF(Q92>=40,"HOLD","SELL")))
A93: 44286 | B93: 14690.7 | C93: 33.2 | D93: Consolidated | E93: =IFERROR(B93/C93,"") | F93: =IF(D93=D89,IFERROR(E93/E89-1,""),"") | G93: =IFERROR((COUNTIF($C$93:$C$114,"<"&C93)+0.5*COUNTIF($C$93:$C$114,C93))/COUNT($C$93:$C$114),"") | H93: =IF(G93="","",IF(G93<=20%,"Q1 Cheapest",IF(G93<=40%,"Q2",IF(G93<=60%,"Q3",IF(G93<=80%,"Q4","Q5 Most Expensive"))))) | I93: =IFERROR(B97/B93-1,"") | J93: =IFERROR((B105/B93)^(1/3)-1,"") | K93: =IFERROR((B113/B93)^(1/5)-1,"") | M93: =IF(F93="","",IF(F93<5%,"<5%",IF(F93<15%,"5-15%",">15%"))) | N93: =IF(COUNT($C$93:C93)<8,"",(COUNTIF($C$93:C93,"<"&C93)+0.5*COUNTIF($C$93:C93,C93))/COUNT($C$93:C93)) | O93: =IF(N93="","",100*(1-N93)) | P93: =IF(F93="","",IF(F93<=0,20,IF(F93<5%,20+400*F93,IF(F93<10%,40+400*(F93-5%),IF(F93<15%,60+400*(F93-10%),IF(F93<25%,80+200*(F93-15%),100)))))) | Q93: =IF(OR(O93="",P93=""),"",70%*O93+30%*P93) | R93: =IF(Q93="","",IF(Q93>=70,"BUY",IF(Q93>=40,"HOLD","SELL")))
A94: 44377 | B94: 15721.5 | C94: 28.3 | D94: Consolidated | E94: =IFERROR(B94/C94,"") | F94: =IF(D94=D90,IFERROR(E94/E90-1,""),"") | G94: =IFERROR((COUNTIF($C$93:$C$114,"<"&C94)+0.5*COUNTIF($C$93:$C$114,C94))/COUNT($C$93:$C$114),"") | H94: =IF(G94="","",IF(G94<=20%,"Q1 Cheapest",IF(G94<=40%,"Q2",IF(G94<=60%,"Q3",IF(G94<=80%,"Q4","Q5 Most Expensive"))))) | I94: =IFERROR(B98/B94-1,"") | J94: =IFERROR((B106/B94)^(1/3)-1,"") | K94: =IFERROR((B114/B94)^(1/5)-1,"") | M94: =IF(F94="","",IF(F94<5%,"<5%",IF(F94<15%,"5-15%",">15%"))) | N94: =IF(COUNT($C$93:C94)<8,"",(COUNTIF($C$93:C94,"<"&C94)+0.5*COUNTIF($C$93:C94,C94))/COUNT($C$93:C94)) | O94: =IF(N94="","",100*(1-N94)) | P94: =IF(F94="","",IF(F94<=0,20,IF(F94<5%,20+400*F94,IF(F94<10%,40+400*(F94-5%),IF(F94<15%,60+400*(F94-10%),IF(F94<25%,80+200*(F94-15%),100)))))) | Q94: =IF(OR(O94="",P94=""),"",70%*O94+30%*P94) | R94: =IF(Q94="","",IF(Q94>=70,"BUY",IF(Q94>=40,"HOLD","SELL")))
A95: 44469 | B95: 17618.15 | C95: 27 | D95: Consolidated | E95: =IFERROR(B95/C95,"") | F95: =IF(D95=D91,IFERROR(E95/E91-1,""),"") | G95: =IFERROR((COUNTIF($C$93:$C$114,"<"&C95)+0.5*COUNTIF($C$93:$C$114,C95))/COUNT($C$93:$C$114),"") | H95: =IF(G95="","",IF(G95<=20%,"Q1 Cheapest",IF(G95<=40%,"Q2",IF(G95<=60%,"Q3",IF(G95<=80%,"Q4","Q5 Most Expensive"))))) | I95: =IFERROR(B99/B95-1,"") | J95: =IFERROR((B107/B95)^(1/3)-1,"") | M95: =IF(F95="","",IF(F95<5%,"<5%",IF(F95<15%,"5-15%",">15%"))) | N95: =IF(COUNT($C$93:C95)<8,"",(COUNTIF($C$93:C95,"<"&C95)+0.5*COUNTIF($C$93:C95,C95))/COUNT($C$93:C95)) | O95: =IF(N95="","",100*(1-N95)) | P95: =IF(F95="","",IF(F95<=0,20,IF(F95<5%,20+400*F95,IF(F95<10%,40+400*(F95-5%),IF(F95<15%,60+400*(F95-10%),IF(F95<25%,80+200*(F95-15%),100)))))) | Q95: =IF(OR(O95="",P95=""),"",70%*O95+30%*P95) | R95: =IF(Q95="","",IF(Q95>=70,"BUY",IF(Q95>=40,"HOLD","SELL")))
A96: 44561 | B96: 17354.05 | C96: 24.1 | D96: Consolidated | E96: =IFERROR(B96/C96,"") | F96: =IF(D96=D92,IFERROR(E96/E92-1,""),"") | G96: =IFERROR((COUNTIF($C$93:$C$114,"<"&C96)+0.5*COUNTIF($C$93:$C$114,C96))/COUNT($C$93:$C$114),"") | H96: =IF(G96="","",IF(G96<=20%,"Q1 Cheapest",IF(G96<=40%,"Q2",IF(G96<=60%,"Q3",IF(G96<=80%,"Q4","Q5 Most Expensive"))))) | I96: =IFERROR(B100/B96-1,"") | J96: =IFERROR((B108/B96)^(1/3)-1,"") | M96: =IF(F96="","",IF(F96<5%,"<5%",IF(F96<15%,"5-15%",">15%"))) | N96: =IF(COUNT($C$93:C96)<8,"",(COUNTIF($C$93:C96,"<"&C96)+0.5*COUNTIF($C$93:C96,C96))/COUNT($C$93:C96)) | O96: =IF(N96="","",100*(1-N96)) | P96: =IF(F96="","",IF(F96<=0,20,IF(F96<5%,20+400*F96,IF(F96<10%,40+400*(F96-5%),IF(F96<15%,60+400*(F96-10%),IF(F96<25%,80+200*(F96-15%),100)))))) | Q96: =IF(OR(O96="",P96=""),"",70%*O96+30%*P96) | R96: =IF(Q96="","",IF(Q96>=70,"BUY",IF(Q96>=40,"HOLD","SELL")))
A97: 44651 | B97: 17464.75 | C97: 22.9 | D97: Consolidated | E97: =IFERROR(B97/C97,"") | F97: =IF(D97=D93,IFERROR(E97/E93-1,""),"") | G97: =IFERROR((COUNTIF($C$93:$C$114,"<"&C97)+0.5*COUNTIF($C$93:$C$114,C97))/COUNT($C$93:$C$114),"") | H97: =IF(G97="","",IF(G97<=20%,"Q1 Cheapest",IF(G97<=40%,"Q2",IF(G97<=60%,"Q3",IF(G97<=80%,"Q4","Q5 Most Expensive"))))) | I97: =IFERROR(B101/B97-1,"") | J97: =IFERROR((B109/B97)^(1/3)-1,"") | M97: =IF(F97="","",IF(F97<5%,"<5%",IF(F97<15%,"5-15%",">15%"))) | N97: =IF(COUNT($C$93:C97)<8,"",(COUNTIF($C$93:C97,"<"&C97)+0.5*COUNTIF($C$93:C97,C97))/COUNT($C$93:C97)) | O97: =IF(N97="","",100*(1-N97)) | P97: =IF(F97="","",IF(F97<=0,20,IF(F97<5%,20+400*F97,IF(F97<10%,40+400*(F97-5%),IF(F97<15%,60+400*(F97-10%),IF(F97<25%,80+200*(F97-15%),100)))))) | Q97: =IF(OR(O97="",P97=""),"",70%*O97+30%*P97) | R97: =IF(Q97="","",IF(Q97>=70,"BUY",IF(Q97>=40,"HOLD","SELL")))
A98: 44742 | B98: 15780.25 | C98: 19.5 | D98: Consolidated | E98: =IFERROR(B98/C98,"") | F98: =IF(D98=D94,IFERROR(E98/E94-1,""),"") | G98: =IFERROR((COUNTIF($C$93:$C$114,"<"&C98)+0.5*COUNTIF($C$93:$C$114,C98))/COUNT($C$93:$C$114),"") | H98: =IF(G98="","",IF(G98<=20%,"Q1 Cheapest",IF(G98<=40%,"Q2",IF(G98<=60%,"Q3",IF(G98<=80%,"Q4","Q5 Most Expensive"))))) | I98: =IFERROR(B102/B98-1,"") | J98: =IFERROR((B110/B98)^(1/3)-1,"") | M98: =IF(F98="","",IF(F98<5%,"<5%",IF(F98<15%,"5-15%",">15%"))) | N98: =IF(COUNT($C$93:C98)<8,"",(COUNTIF($C$93:C98,"<"&C98)+0.5*COUNTIF($C$93:C98,C98))/COUNT($C$93:C98)) | O98: =IF(N98="","",100*(1-N98)) | P98: =IF(F98="","",IF(F98<=0,20,IF(F98<5%,20+400*F98,IF(F98<10%,40+400*(F98-5%),IF(F98<15%,60+400*(F98-10%),IF(F98<25%,80+200*(F98-15%),100)))))) | Q98: =IF(OR(O98="",P98=""),"",70%*O98+30%*P98) | R98: =IF(Q98="","",IF(Q98>=70,"BUY",IF(Q98>=40,"HOLD","SELL")))
A99: 44834 | B99: 17094.35 | C99: 20.6 | D99: Consolidated | E99: =IFERROR(B99/C99,"") | F99: =IF(D99=D95,IFERROR(E99/E95-1,""),"") | G99: =IFERROR((COUNTIF($C$93:$C$114,"<"&C99)+0.5*COUNTIF($C$93:$C$114,C99))/COUNT($C$93:$C$114),"") | H99: =IF(G99="","",IF(G99<=20%,"Q1 Cheapest",IF(G99<=40%,"Q2",IF(G99<=60%,"Q3",IF(G99<=80%,"Q4","Q5 Most Expensive"))))) | I99: =IFERROR(B103/B99-1,"") | J99: =IFERROR((B111/B99)^(1/3)-1,"") | M99: =IF(F99="","",IF(F99<5%,"<5%",IF(F99<15%,"5-15%",">15%"))) | N99: =IF(COUNT($C$93:C99)<8,"",(COUNTIF($C$93:C99,"<"&C99)+0.5*COUNTIF($C$93:C99,C99))/COUNT($C$93:C99)) | O99: =IF(N99="","",100*(1-N99)) | P99: =IF(F99="","",IF(F99<=0,20,IF(F99<5%,20+400*F99,IF(F99<10%,40+400*(F99-5%),IF(F99<15%,60+400*(F99-10%),IF(F99<25%,80+200*(F99-15%),100)))))) | Q99: =IF(OR(O99="",P99=""),"",70%*O99+30%*P99) | R99: =IF(Q99="","",IF(Q99>=70,"BUY",IF(Q99>=40,"HOLD","SELL")))
A100: 44926 | B100: 18105.3 | C100: 21.8 | D100: Consolidated | E100: =IFERROR(B100/C100,"") | F100: =IF(D100=D96,IFERROR(E100/E96-1,""),"") | G100: =IFERROR((COUNTIF($C$93:$C$114,"<"&C100)+0.5*COUNTIF($C$93:$C$114,C100))/COUNT($C$93:$C$114),"") | H100: =IF(G100="","",IF(G100<=20%,"Q1 Cheapest",IF(G100<=40%,"Q2",IF(G100<=60%,"Q3",IF(G100<=80%,"Q4","Q5 Most Expensive"))))) | I100: =IFERROR(B104/B100-1,"") | J100: =IFERROR((B112/B100)^(1/3)-1,"") | M100: =IF(F100="","",IF(F100<5%,"<5%",IF(F100<15%,"5-15%",">15%"))) | N100: =IF(COUNT($C$93:C100)<8,"",(COUNTIF($C$93:C100,"<"&C100)+0.5*COUNTIF($C$93:C100,C100))/COUNT($C$93:C100)) | O100: =IF(N100="","",100*(1-N100)) | P100: =IF(F100="","",IF(F100<=0,20,IF(F100<5%,20+400*F100,IF(F100<10%,40+400*(F100-5%),IF(F100<15%,60+400*(F100-10%),IF(F100<25%,80+200*(F100-15%),100)))))) | Q100: =IF(OR(O100="",P100=""),"",70%*O100+30%*P100) | R100: =IF(Q100="","",IF(Q100>=70,"BUY",IF(Q100>=40,"HOLD","SELL")))
A101: 45016 | B101: 17359.75 | C101: 20.4 | D101: Consolidated | E101: =IFERROR(B101/C101,"") | F101: =IF(D101=D97,IFERROR(E101/E97-1,""),"") | G101: =IFERROR((COUNTIF($C$93:$C$114,"<"&C101)+0.5*COUNTIF($C$93:$C$114,C101))/COUNT($C$93:$C$114),"") | H101: =IF(G101="","",IF(G101<=20%,"Q1 Cheapest",IF(G101<=40%,"Q2",IF(G101<=60%,"Q3",IF(G101<=80%,"Q4","Q5 Most Expensive"))))) | I101: =IFERROR(B105/B101-1,"") | J101: =IFERROR((B113/B101)^(1/3)-1,"") | M101: =IF(F101="","",IF(F101<5%,"<5%",IF(F101<15%,"5-15%",">15%"))) | N101: =IF(COUNT($C$93:C101)<8,"",(COUNTIF($C$93:C101,"<"&C101)+0.5*COUNTIF($C$93:C101,C101))/COUNT($C$93:C101)) | O101: =IF(N101="","",100*(1-N101)) | P101: =IF(F101="","",IF(F101<=0,20,IF(F101<5%,20+400*F101,IF(F101<10%,40+400*(F101-5%),IF(F101<15%,60+400*(F101-10%),IF(F101<25%,80+200*(F101-15%),100)))))) | Q101: =IF(OR(O101="",P101=""),"",70%*O101+30%*P101) | R101: =IF(Q101="","",IF(Q101>=70,"BUY",IF(Q101>=40,"HOLD","SELL")))
A102: 45107 | B102: 19189.05 | C102: 22.4 | D102: Consolidated | E102: =IFERROR(B102/C102,"") | F102: =IF(D102=D98,IFERROR(E102/E98-1,""),"") | G102: =IFERROR((COUNTIF($C$93:$C$114,"<"&C102)+0.5*COUNTIF($C$93:$C$114,C102))/COUNT($C$93:$C$114),"") | H102: =IF(G102="","",IF(G102<=20%,"Q1 Cheapest",IF(G102<=40%,"Q2",IF(G102<=60%,"Q3",IF(G102<=80%,"Q4","Q5 Most Expensive"))))) | I102: =IFERROR(B106/B102-1,"") | J102: =IFERROR((B114/B102)^(1/3)-1,"") | M102: =IF(F102="","",IF(F102<5%,"<5%",IF(F102<15%,"5-15%",">15%"))) | N102: =IF(COUNT($C$93:C102)<8,"",(COUNTIF($C$93:C102,"<"&C102)+0.5*COUNTIF($C$93:C102,C102))/COUNT($C$93:C102)) | O102: =IF(N102="","",100*(1-N102)) | P102: =IF(F102="","",IF(F102<=0,20,IF(F102<5%,20+400*F102,IF(F102<10%,40+400*(F102-5%),IF(F102<15%,60+400*(F102-10%),IF(F102<25%,80+200*(F102-15%),100)))))) | Q102: =IF(OR(O102="",P102=""),"",70%*O102+30%*P102) | R102: =IF(Q102="","",IF(Q102>=70,"BUY",IF(Q102>=40,"HOLD","SELL")))
A103: 45199 | B103: 19638.3 | C103: 22.2 | D103: Consolidated | E103: =IFERROR(B103/C103,"") | F103: =IF(D103=D99,IFERROR(E103/E99-1,""),"") | G103: =IFERROR((COUNTIF($C$93:$C$114,"<"&C103)+0.5*COUNTIF($C$93:$C$114,C103))/COUNT($C$93:$C$114),"") | H103: =IF(G103="","",IF(G103<=20%,"Q1 Cheapest",IF(G103<=40%,"Q2",IF(G103<=60%,"Q3",IF(G103<=80%,"Q4","Q5 Most Expensive"))))) | I103: =IFERROR(B107/B103-1,"") | M103: =IF(F103="","",IF(F103<5%,"<5%",IF(F103<15%,"5-15%",">15%"))) | N103: =IF(COUNT($C$93:C103)<8,"",(COUNTIF($C$93:C103,"<"&C103)+0.5*COUNTIF($C$93:C103,C103))/COUNT($C$93:C103)) | O103: =IF(N103="","",100*(1-N103)) | P103: =IF(F103="","",IF(F103<=0,20,IF(F103<5%,20+400*F103,IF(F103<10%,40+400*(F103-5%),IF(F103<15%,60+400*(F103-10%),IF(F103<25%,80+200*(F103-15%),100)))))) | Q103: =IF(OR(O103="",P103=""),"",70%*O103+30%*P103) | R103: =IF(Q103="","",IF(Q103>=70,"BUY",IF(Q103>=40,"HOLD","SELL")))
A104: 45291 | B104: 21731.4 | C104: 23.2 | D104: Consolidated | E104: =IFERROR(B104/C104,"") | F104: =IF(D104=D100,IFERROR(E104/E100-1,""),"") | G104: =IFERROR((COUNTIF($C$93:$C$114,"<"&C104)+0.5*COUNTIF($C$93:$C$114,C104))/COUNT($C$93:$C$114),"") | H104: =IF(G104="","",IF(G104<=20%,"Q1 Cheapest",IF(G104<=40%,"Q2",IF(G104<=60%,"Q3",IF(G104<=80%,"Q4","Q5 Most Expensive"))))) | I104: =IFERROR(B108/B104-1,"") | M104: =IF(F104="","",IF(F104<5%,"<5%",IF(F104<15%,"5-15%",">15%"))) | N104: =IF(COUNT($C$93:C104)<8,"",(COUNTIF($C$93:C104,"<"&C104)+0.5*COUNTIF($C$93:C104,C104))/COUNT($C$93:C104)) | O104: =IF(N104="","",100*(1-N104)) | P104: =IF(F104="","",IF(F104<=0,20,IF(F104<5%,20+400*F104,IF(F104<10%,40+400*(F104-5%),IF(F104<15%,60+400*(F104-10%),IF(F104<25%,80+200*(F104-15%),100)))))) | Q104: =IF(OR(O104="",P104=""),"",70%*O104+30%*P104) | R104: =IF(Q104="","",IF(Q104>=70,"BUY",IF(Q104>=40,"HOLD","SELL")))
A105: 45382 | B105: 22326.9 | C105: 22.9 | D105: Consolidated | E105: =IFERROR(B105/C105,"") | F105: =IF(D105=D101,IFERROR(E105/E101-1,""),"") | G105: =IFERROR((COUNTIF($C$93:$C$114,"<"&C105)+0.5*COUNTIF($C$93:$C$114,C105))/COUNT($C$93:$C$114),"") | H105: =IF(G105="","",IF(G105<=20%,"Q1 Cheapest",IF(G105<=40%,"Q2",IF(G105<=60%,"Q3",IF(G105<=80%,"Q4","Q5 Most Expensive"))))) | I105: =IFERROR(B109/B105-1,"") | M105: =IF(F105="","",IF(F105<5%,"<5%",IF(F105<15%,"5-15%",">15%"))) | N105: =IF(COUNT($C$93:C105)<8,"",(COUNTIF($C$93:C105,"<"&C105)+0.5*COUNTIF($C$93:C105,C105))/COUNT($C$93:C105)) | O105: =IF(N105="","",100*(1-N105)) | P105: =IF(F105="","",IF(F105<=0,20,IF(F105<5%,20+400*F105,IF(F105<10%,40+400*(F105-5%),IF(F105<15%,60+400*(F105-10%),IF(F105<25%,80+200*(F105-15%),100)))))) | Q105: =IF(OR(O105="",P105=""),"",70%*O105+30%*P105) | R105: =IF(Q105="","",IF(Q105>=70,"BUY",IF(Q105>=40,"HOLD","SELL")))
A106: 45473 | B106: 24010.6 | C106: 22.9 | D106: Consolidated | E106: =IFERROR(B106/C106,"") | F106: =IF(D106=D102,IFERROR(E106/E102-1,""),"") | G106: =IFERROR((COUNTIF($C$93:$C$114,"<"&C106)+0.5*COUNTIF($C$93:$C$114,C106))/COUNT($C$93:$C$114),"") | H106: =IF(G106="","",IF(G106<=20%,"Q1 Cheapest",IF(G106<=40%,"Q2",IF(G106<=60%,"Q3",IF(G106<=80%,"Q4","Q5 Most Expensive"))))) | I106: =IFERROR(B110/B106-1,"") | M106: =IF(F106="","",IF(F106<5%,"<5%",IF(F106<15%,"5-15%",">15%"))) | N106: =IF(COUNT($C$93:C106)<8,"",(COUNTIF($C$93:C106,"<"&C106)+0.5*COUNTIF($C$93:C106,C106))/COUNT($C$93:C106)) | O106: =IF(N106="","",100*(1-N106)) | P106: =IF(F106="","",IF(F106<=0,20,IF(F106<5%,20+400*F106,IF(F106<10%,40+400*(F106-5%),IF(F106<15%,60+400*(F106-10%),IF(F106<25%,80+200*(F106-15%),100)))))) | Q106: =IF(OR(O106="",P106=""),"",70%*O106+30%*P106) | R106: =IF(Q106="","",IF(Q106>=70,"BUY",IF(Q106>=40,"HOLD","SELL")))
A107: 45565 | B107: 26061.3 | C107: 24.3 | D107: Consolidated | E107: =IFERROR(B107/C107,"") | F107: =IF(D107=D103,IFERROR(E107/E103-1,""),"") | G107: =IFERROR((COUNTIF($C$93:$C$114,"<"&C107)+0.5*COUNTIF($C$93:$C$114,C107))/COUNT($C$93:$C$114),"") | H107: =IF(G107="","",IF(G107<=20%,"Q1 Cheapest",IF(G107<=40%,"Q2",IF(G107<=60%,"Q3",IF(G107<=80%,"Q4","Q5 Most Expensive"))))) | I107: =IFERROR(B111/B107-1,"") | M107: =IF(F107="","",IF(F107<5%,"<5%",IF(F107<15%,"5-15%",">15%"))) | N107: =IF(COUNT($C$93:C107)<8,"",(COUNTIF($C$93:C107,"<"&C107)+0.5*COUNTIF($C$93:C107,C107))/COUNT($C$93:C107)) | O107: =IF(N107="","",100*(1-N107)) | P107: =IF(F107="","",IF(F107<=0,20,IF(F107<5%,20+400*F107,IF(F107<10%,40+400*(F107-5%),IF(F107<15%,60+400*(F107-10%),IF(F107<25%,80+200*(F107-15%),100)))))) | Q107: =IF(OR(O107="",P107=""),"",70%*O107+30%*P107) | R107: =IF(Q107="","",IF(Q107>=70,"BUY",IF(Q107>=40,"HOLD","SELL")))
A108: 45657 | B108: 23560.6 | C108: 21.8 | D108: Consolidated | E108: =IFERROR(B108/C108,"") | F108: =IF(D108=D104,IFERROR(E108/E104-1,""),"") | G108: =IFERROR((COUNTIF($C$93:$C$114,"<"&C108)+0.5*COUNTIF($C$93:$C$114,C108))/COUNT($C$93:$C$114),"") | H108: =IF(G108="","",IF(G108<=20%,"Q1 Cheapest",IF(G108<=40%,"Q2",IF(G108<=60%,"Q3",IF(G108<=80%,"Q4","Q5 Most Expensive"))))) | I108: =IFERROR(B112/B108-1,"") | M108: =IF(F108="","",IF(F108<5%,"<5%",IF(F108<15%,"5-15%",">15%"))) | N108: =IF(COUNT($C$93:C108)<8,"",(COUNTIF($C$93:C108,"<"&C108)+0.5*COUNTIF($C$93:C108,C108))/COUNT($C$93:C108)) | O108: =IF(N108="","",100*(1-N108)) | P108: =IF(F108="","",IF(F108<=0,20,IF(F108<5%,20+400*F108,IF(F108<10%,40+400*(F108-5%),IF(F108<15%,60+400*(F108-10%),IF(F108<25%,80+200*(F108-15%),100)))))) | Q108: =IF(OR(O108="",P108=""),"",70%*O108+30%*P108) | R108: =IF(Q108="","",IF(Q108>=70,"BUY",IF(Q108>=40,"HOLD","SELL")))
A109: 45747 | B109: 23519.35 | C109: 21.4 | D109: Consolidated | E109: =IFERROR(B109/C109,"") | F109: =IF(D109=D105,IFERROR(E109/E105-1,""),"") | G109: =IFERROR((COUNTIF($C$93:$C$114,"<"&C109)+0.5*COUNTIF($C$93:$C$114,C109))/COUNT($C$93:$C$114),"") | H109: =IF(G109="","",IF(G109<=20%,"Q1 Cheapest",IF(G109<=40%,"Q2",IF(G109<=60%,"Q3",IF(G109<=80%,"Q4","Q5 Most Expensive"))))) | I109: =IFERROR(B113/B109-1,"") | M109: =IF(F109="","",IF(F109<5%,"<5%",IF(F109<15%,"5-15%",">15%"))) | N109: =IF(COUNT($C$93:C109)<8,"",(COUNTIF($C$93:C109,"<"&C109)+0.5*COUNTIF($C$93:C109,C109))/COUNT($C$93:C109)) | O109: =IF(N109="","",100*(1-N109)) | P109: =IF(F109="","",IF(F109<=0,20,IF(F109<5%,20+400*F109,IF(F109<10%,40+400*(F109-5%),IF(F109<15%,60+400*(F109-10%),IF(F109<25%,80+200*(F109-15%),100)))))) | Q109: =IF(OR(O109="",P109=""),"",70%*O109+30%*P109) | R109: =IF(Q109="","",IF(Q109>=70,"BUY",IF(Q109>=40,"HOLD","SELL")))
A110: 45838 | B110: 25517.05 | C110: 23 | D110: Consolidated | E110: =IFERROR(B110/C110,"") | F110: =IF(D110=D106,IFERROR(E110/E106-1,""),"") | G110: =IFERROR((COUNTIF($C$93:$C$114,"<"&C110)+0.5*COUNTIF($C$93:$C$114,C110))/COUNT($C$93:$C$114),"") | H110: =IF(G110="","",IF(G110<=20%,"Q1 Cheapest",IF(G110<=40%,"Q2",IF(G110<=60%,"Q3",IF(G110<=80%,"Q4","Q5 Most Expensive"))))) | I110: =IFERROR(B114/B110-1,"") | M110: =IF(F110="","",IF(F110<5%,"<5%",IF(F110<15%,"5-15%",">15%"))) | N110: =IF(COUNT($C$93:C110)<8,"",(COUNTIF($C$93:C110,"<"&C110)+0.5*COUNTIF($C$93:C110,C110))/COUNT($C$93:C110)) | O110: =IF(N110="","",100*(1-N110)) | P110: =IF(F110="","",IF(F110<=0,20,IF(F110<5%,20+400*F110,IF(F110<10%,40+400*(F110-5%),IF(F110<15%,60+400*(F110-10%),IF(F110<25%,80+200*(F110-15%),100)))))) | Q110: =IF(OR(O110="",P110=""),"",70%*O110+30%*P110) | R110: =IF(Q110="","",IF(Q110>=70,"BUY",IF(Q110>=40,"HOLD","SELL")))
A111: 45930 | B111: 24691.95 | C111: 21.8 | D111: Consolidated | E111: =IFERROR(B111/C111,"") | F111: =IF(D111=D107,IFERROR(E111/E107-1,""),"") | G111: =IFERROR((COUNTIF($C$93:$C$114,"<"&C111)+0.5*COUNTIF($C$93:$C$114,C111))/COUNT($C$93:$C$114),"") | H111: =IF(G111="","",IF(G111<=20%,"Q1 Cheapest",IF(G111<=40%,"Q2",IF(G111<=60%,"Q3",IF(G111<=80%,"Q4","Q5 Most Expensive"))))) | M111: =IF(F111="","",IF(F111<5%,"<5%",IF(F111<15%,"5-15%",">15%"))) | N111: =IF(COUNT($C$93:C111)<8,"",(COUNTIF($C$93:C111,"<"&C111)+0.5*COUNTIF($C$93:C111,C111))/COUNT($C$93:C111)) | O111: =IF(N111="","",100*(1-N111)) | P111: =IF(F111="","",IF(F111<=0,20,IF(F111<5%,20+400*F111,IF(F111<10%,40+400*(F111-5%),IF(F111<15%,60+400*(F111-10%),IF(F111<25%,80+200*(F111-15%),100)))))) | Q111: =IF(OR(O111="",P111=""),"",70%*O111+30%*P111) | R111: =IF(Q111="","",IF(Q111>=70,"BUY",IF(Q111>=40,"HOLD","SELL")))
A112: 46022 | B112: 25971.05 | C112: 22.8 | D112: Consolidated | E112: =IFERROR(B112/C112,"") | F112: =IF(D112=D108,IFERROR(E112/E108-1,""),"") | G112: =IFERROR((COUNTIF($C$93:$C$114,"<"&C112)+0.5*COUNTIF($C$93:$C$114,C112))/COUNT($C$93:$C$114),"") | H112: =IF(G112="","",IF(G112<=20%,"Q1 Cheapest",IF(G112<=40%,"Q2",IF(G112<=60%,"Q3",IF(G112<=80%,"Q4","Q5 Most Expensive"))))) | M112: =IF(F112="","",IF(F112<5%,"<5%",IF(F112<15%,"5-15%",">15%"))) | N112: =IF(COUNT($C$93:C112)<8,"",(COUNTIF($C$93:C112,"<"&C112)+0.5*COUNTIF($C$93:C112,C112))/COUNT($C$93:C112)) | O112: =IF(N112="","",100*(1-N112)) | P112: =IF(F112="","",IF(F112<=0,20,IF(F112<5%,20+400*F112,IF(F112<10%,40+400*(F112-5%),IF(F112<15%,60+400*(F112-10%),IF(F112<25%,80+200*(F112-15%),100)))))) | Q112: =IF(OR(O112="",P112=""),"",70%*O112+30%*P112) | R112: =IF(Q112="","",IF(Q112>=70,"BUY",IF(Q112>=40,"HOLD","SELL")))
A113: 46112 | B113: 22549.65 | C113: 19.6 | D113: Consolidated | E113: =IFERROR(B113/C113,"") | F113: =IF(D113=D109,IFERROR(E113/E109-1,""),"") | G113: =IFERROR((COUNTIF($C$93:$C$114,"<"&C113)+0.5*COUNTIF($C$93:$C$114,C113))/COUNT($C$93:$C$114),"") | H113: =IF(G113="","",IF(G113<=20%,"Q1 Cheapest",IF(G113<=40%,"Q2",IF(G113<=60%,"Q3",IF(G113<=80%,"Q4","Q5 Most Expensive"))))) | M113: =IF(F113="","",IF(F113<5%,"<5%",IF(F113<15%,"5-15%",">15%"))) | N113: =IF(COUNT($C$93:C113)<8,"",(COUNTIF($C$93:C113,"<"&C113)+0.5*COUNTIF($C$93:C113,C113))/COUNT($C$93:C113)) | O113: =IF(N113="","",100*(1-N113)) | P113: =IF(F113="","",IF(F113<=0,20,IF(F113<5%,20+400*F113,IF(F113<10%,40+400*(F113-5%),IF(F113<15%,60+400*(F113-10%),IF(F113<25%,80+200*(F113-15%),100)))))) | Q113: =IF(OR(O113="",P113=""),"",70%*O113+30%*P113) | R113: =IF(Q113="","",IF(Q113>=70,"BUY",IF(Q113>=40,"HOLD","SELL")))
A114: 46203 | B114: 23865.75 | C114: 20.6 | D114: Consolidated | E114: =IFERROR(B114/C114,"") | F114: =IF(D114=D110,IFERROR(E114/E110-1,""),"") | G114: =IFERROR((COUNTIF($C$93:$C$114,"<"&C114)+0.5*COUNTIF($C$93:$C$114,C114))/COUNT($C$93:$C$114),"") | H114: =IF(G114="","",IF(G114<=20%,"Q1 Cheapest",IF(G114<=40%,"Q2",IF(G114<=60%,"Q3",IF(G114<=80%,"Q4","Q5 Most Expensive"))))) | M114: =IF(F114="","",IF(F114<5%,"<5%",IF(F114<15%,"5-15%",">15%"))) | N114: =IF(COUNT($C$93:C114)<8,"",(COUNTIF($C$93:C114,"<"&C114)+0.5*COUNTIF($C$93:C114,C114))/COUNT($C$93:C114)) | O114: =IF(N114="","",100*(1-N114)) | P114: =IF(F114="","",IF(F114<=0,20,IF(F114<5%,20+400*F114,IF(F114<10%,40+400*(F114-5%),IF(F114<15%,60+400*(F114-10%),IF(F114<25%,80+200*(F114-15%),100)))))) | Q114: =IF(OR(O114="",P114=""),"",70%*O114+30%*P114) | R114: =IF(Q114="","",IF(Q114>=70,"BUY",IF(Q114>=40,"HOLD","SELL")))

Sheet PE_History_Post2021
A1: NIFTY 50 Consolidated-Earnings P/E History
A2: Monthly readings used to locate the current P/E within the post-methodology-change era. The current month is updated through the latest available trading day.
A4: Month | B4: P/E | C4: Basis | D4: Source
A5: 44287 | B5: 32.2 | C5: Consolidated | D5: https://downstox.com/nifty-pe/nifty-50
A6: 44317 | B6: 29.2 | C6: Consolidated | D6: https://downstox.com/nifty-pe/nifty-50
A7: 44348 | B7: 28.3 | C7: Consolidated | D7: https://downstox.com/nifty-pe/nifty-50
A8: 44378 | B8: 27 | C8: Consolidated | D8: https://downstox.com/nifty-pe/nifty-50
A9: 44409 | B9: 26.3 | C9: Consolidated | D9: https://downstox.com/nifty-pe/nifty-50
A10: 44440 | B10: 27 | C10: Consolidated | D10: https://downstox.com/nifty-pe/nifty-50
A11: 44470 | B11: 25.7 | C11: Consolidated | D11: https://downstox.com/nifty-pe/nifty-50
A12: 44501 | B12: 23.4 | C12: Consolidated | D12: https://downstox.com/nifty-pe/nifty-50
A13: 44531 | B13: 24.1 | C13: Consolidated | D13: https://downstox.com/nifty-pe/nifty-50
A14: 44562 | B14: 23.4 | C14: Consolidated | D14: https://downstox.com/nifty-pe/nifty-50
A15: 44593 | B15: 21.6 | C15: Consolidated | D15: https://downstox.com/nifty-pe/nifty-50
A16: 44621 | B16: 22.9 | C16: Consolidated | D16: https://downstox.com/nifty-pe/nifty-50
... A70: 46283 | B70: 19.74 | C70: Consolidated | D70: https://downstox.com/nifty-pe/nifty-50

Sheet Daily_Log
A1: Daily Signal Log
A2: The updater script appends one row per refresh. This sheet is intentionally empty except for the seed row below.
A4: Date | B4: NIFTY Close | C4: P/E | D4: P/E Percentile | E4: Implied EPS | F4: YoY EPS Growth | G4: Valuation Score | H4: Growth Score | I4: Composite Score | J4: Signal | K4: PE Source | L4: Price Source
A5: =Dashboard!B5 | B5: =Dashboard!B6 | C5: =Dashboard!B7 | D5: =Dashboard!B9 | E5: =Dashboard!B11 | F5: =Dashboard!B16 | G5: =Dashboard!B17 | H5: =Dashboard!B18 | I5: =Dashboard!B19 | J5: =Dashboard!B20 | K5: https://downstox.com/nifty-pe/nifty-50 | L5: https://finance.yahoo.com/quote/%5ENSEI/history/

Sheet Methodology
A1: Methodology, Sources & Limitations
A2: Read this sheet before using the daily signal. The model is designed for strategic NIFTY allocation, not short-term trading.
A4: 1. WHY THE P/E HISTORY IS SPLIT
A5: NSE changed the index P/E earnings basis effective 31 March 2021 from standalone earnings to trailing-four-quarter consolidated earnings where available. Raw P/E values across the seam are therefore not directly comparable. The historical backtest ranks each observation only within its own earnings-methodology regime before pooling outcomes.
A9: 2. BACKTEST DESIGN
A10: Sampling | B10: Quarter-end observations from Mar-1999 to Jun-2026. This reduces, but does not eliminate, overlapping forward-return windows.
A11: Valuation normalisation | B11: Empirical P/E percentile within the relevant regime. Q1 is the cheapest 20%; Q5 is the most expensive 20%.
A12: Forward returns | B12: NIFTY 50 Price Return Index: 1Y total price return; 3Y/5Y/10Y annualised CAGR. Dividends are excluded.
A13: EPS proxy | B13: Implied index EPS = NIFTY level / published P/E. YoY growth is only calculated when both observations use the same P/E methodology.
A14: Signal backtest | B14: Uses an expanding (no-lookahead) P/E percentile within the regime, with at least 8 observations before a signal is produced.
A15: Current live signal | B15: Uses current consolidated-era P/E percentile plus approximate YoY implied EPS growth. The current PE changes daily; the growth comparator is month-based and therefore slower-moving.
A18: 3. SIGNAL INTERPRETATION
A19: BUY | B19: Composite score ≥70. Historically favourable valuation/growth mix; interpreted as favourable for gradual long-term allocation.
A20: HOLD | B20: 40–69.9. Maintain strategic allocation; neither valuation nor growth provides a sufficiently strong tilt.
A21: SELL | B21: <40. Reduce or avoid incremental allocation. It does NOT mean short the NIFTY or liquidate a diversified long-term portfolio.
A22: Weights | B22: 70% valuation / 30% earnings growth by design. The weights are deliberately simple and interpretable rather than optimised to maximise historical returns.
A25: 4. SOURCES
A26: NSE P/E methodology | B26: https://www.niftyindices.com/resources/index-concepts/price-earnings-ratio
A27: NSE historical reports | B27: https://www.niftyindices.com/reports
A28: NSE daily reports | B28: https://www.niftyindices.com/reports/daily-reports
A29: P/E history used | B29: https://downstox.com/nifty-pe/nifty-50
A30: P/E CSV endpoint | B30: https://downstox.com/api/index-pe/nifty-50/download
A31: Historical NIFTY close used | B31: https://www.sensexindia.in/indices/NIFTY-50-Returns.aspx
A32: Yahoo NIFTY history fallback | B32: https://finance.yahoo.com/quote/%5ENSEI/history/
A35: 5. IMPORTANT LIMITATIONS
A36: This is an empirical valuation model, not a forecast engine. Quarter-end observations still overlap; the post-2021 consolidated regime is short; extreme trailing P/E during COVID was distorted by temporarily depressed earnings; the historical return series used here excludes dividends; and tax, transaction costs, asset allocation, risk tolerance and investor horizon are outside the model. The model should be used as a valuation/allocation indicator alongside a broader investment process.
